[{"date":"2021-01-08","symbol":"DOC","subkey":"","fClose":16.97,"uOpen":16.8,"uClose":16.97,"high":17.01,"fOpen":16.8,"low":16.77,"changeOverTime":0,"fHigh":17.01,"changePercent":0,"id":"HISTORICAL_PRICES","marketChangeOverTime":0,"close":16.97,"key":"DOC","fLow":16.77,"uHigh":17.01,"uVolume":1886610,"change":0,"uLow":16.77,"fVolume":1886610,"label":"Jan 8, 21","volume":1886610,"updated":1610158570000,"open":16.8},
{"date":"2021-01-07","symbol":"DOC","subkey":"","fClose":16.73,"uOpen":16.79,"uClose":16.73,"high":16.89,"fOpen":16.79,"low":16.57,"changeOverTime":-0.014142604596346402,"fHigh":16.89,"changePercent":-0.0141,"id":"HISTORICAL_PRICES","marketChangeOverTime":-0.014142604596346402,"close":16.73,"key":"DOC","fLow":16.57,"uHigh":16.89,"uVolume":2041914,"change":-0.23999999999999844,"uLow":16.57,"fVolume":2041914,"label":"Jan 7, 21","volume":2041914,"updated":1610072173000,"open":16.79},
{"date":"2021-01-06","symbol":"DOC","subkey":"","fClose":16.89,"uOpen":16.91,"uClose":16.89,"high":17.16,"fOpen":16.91,"low":16.71,"changeOverTime":-0.004714201532115398,"fHigh":17.16,"changePercent":0.0096,"id":"HISTORICAL_PRICES","marketChangeOverTime":-0.004714201532115398,"close":16.89,"key":"DOC","fLow":16.71,"uHigh":17.16,"uVolume":2832458,"change":0.16000000000000014,"uLow":16.71,"fVolume":2832458,"label":"Jan 6, 21","volume":2832458,"updated":1609984801000,"open":16.91},
{"date":"2021-01-05","symbol":"DOC","subkey":"","fClose":16.88,"uOpen":16.83,"uClose":16.88,"high":17.11,"fOpen":16.83,"low":16.83,"changeOverTime":-0.005303476723629927,"fHigh":17.11,"changePercent":-0.0006,"id":"HISTORICAL_PRICES","marketChangeOverTime":-0.005303476723629927,"close":16.88,"key":"DOC","fLow":16.83,"uHigh":17.11,"uVolume":2099297,"change":-0.010000000000001563,"uLow":16.83,"fVolume":2099297,"label":"Jan 5, 21","volume":2099297,"updated":1609897690000,"open":16.83},
{"date":"2021-01-04","symbol":"DOC","subkey":"","fClose":16.76,"uOpen":17.68,"uClose":16.76,"high":17.71,"fOpen":17.68,"low":16.76,"changeOverTime":-0.012374779021803024,"fHigh":17.71,"changePercent":-0.0071,"id":"HISTORICAL_PRICES","marketChangeOverTime":-0.012374779021803024,"close":16.76,"key":"DOC","fLow":16.76,"uHigh":17.71,"uVolume":2825798,"change":-0.11999999999999744,"uLow":16.76,"fVolume":2825798,"label":"Jan 4, 21","volume":2825798,"updated":1609812974000,"open":17.68},
{"date":"2020-12-31","symbol":"DOC","subkey":"","fClose":17.57,"uOpen":17.78,"uClose":17.8,"high":17.84,"fOpen":17.5503,"low":17.6245,"changeOverTime":0.0489098408956984,"fHigh":17.6095,"changePercent":0.0621,"id":"HISTORICAL_PRICES","marketChangeOverTime":0.0489098408956984,"close":17.8,"key":"DOC","fLow":17.3968,"uHigh":17.84,"uVolume":1461019,"change":1.0399999999999991,"uLow":17.6245,"fVolume":1461019,"label":"Dec 31, 20","volume":1461019,"updated":1609813012000,"open":17.78},
{"date":"2020-12-30","symbol":"DOC","subkey":"","fClose":17.5799,"uOpen":17.9,"uClose":17.81,"high":18.14,"fOpen":17.6687,"low":17.78,"changeOverTime":0.049499116087212726,"fHigh":17.9056,"changePercent":0.0006,"id":"HISTORICAL_PRICES","marketChangeOverTime":0.049499116087212726,"close":17.81,"key":"DOC","fLow":17.5503,"uHigh":18.14,"uVolume":1293841,"change":0.00999999999999801,"uLow":17.78,"fVolume":1293841,"label":"Dec 30, 20","volume":1293841,"updated":1609812991000,"open":17.9},
{"date":"2020-12-29","symbol":"DOC","subkey":"","fClose":17.649,"uOpen":18.1,"uClose":17.88,"high":18.18,"fOpen":17.8661,"low":17.78,"changeOverTime":0.0536240424278138,"fHigh":17.9451,"changePercent":0.0039,"id":"HISTORICAL_PRICES","marketChangeOverTime":0.0536240424278138,"close":17.88,"key":"DOC","fLow":17.5503,"uHigh":18.18,"uVolume":1068339,"change":0.07000000000000028,"uLow":17.78,"fVolume":1068339,"label":"Dec 29, 20","volume":1068339,"updated":1609812961000,"open":18.1},
{"date":"2020-12-28","symbol":"DOC","subkey":"","fClose":17.8365,"uOpen":18.04,"uClose":18.07,"high":18.11,"fOpen":17.8069,"low":17.9099,"changeOverTime":0.06482027106658818,"fHigh":17.876,"changePercent":0.0106,"id":"HISTORICAL_PRICES","marketChangeOverTime":0.06482027106658818,"close":18.07,"key":"DOC","fLow":17.6785,"uHigh":18.11,"uVolume":980969,"change":0.19000000000000128,"uLow":17.9099,"fVolume":980969,"label":"Dec 28, 20","volume":980969,"updated":1609813063000,"open":18.04},
{"date":"2020-12-24","symbol":"DOC","subkey":"","fClose":17.7477,"uOpen":17.91,"uClose":17.98,"high":18.01,"fOpen":17.6786,"low":17.805,"changeOverTime":0.05951679434295826,"fHigh":17.7773,"changePercent":-0.005,"id":"HISTORICAL_PRICES","marketChangeOverTime":0.05951679434295826,"close":17.98,"key":"DOC","fLow":17.5749,"uHigh":18.01,"uVolume":415243,"change":-0.08999999999999986,"uLow":17.805,"fVolume":415243,"label":"Dec 24, 20","volume":415243,"updated":1609812976000,"open":17.91},
{"date":"2020-12-23","symbol":"DOC","subkey":"","fClose":17.5996,"uOpen":18.15,"uClose":17.83,"high":18.29,"fOpen":17.9155,"low":17.79,"changeOverTime":0.05067766647024157,"fHigh":18.0537,"changePercent":-0.0083,"id":"HISTORICAL_PRICES","marketChangeOverTime":0.05067766647024157,"close":17.83,"key":"DOC","fLow":17.5601,"uHigh":18.29,"uVolume":1304061,"change":-0.15000000000000213,"uLow":17.79,"fVolume":1304061,"label":"Dec 23, 20","volume":1304061,"updated":1609813063000,"open":18.15},
{"date":"2020-12-22","symbol":"DOC","subkey":"","fClose":17.8563,"uOpen":17.91,"uClose":18.09,"high":18.11,"fOpen":17.6786,"low":17.73,"changeOverTime":0.06599882144961704,"fHigh":17.876,"changePercent":0.0146,"id":"HISTORICAL_PRICES","marketChangeOverTime":0.06599882144961704,"close":18.09,"key":"DOC","fLow":17.5009,"uHigh":18.11,"uVolume":1230433,"change":0.26000000000000156,"uLow":17.73,"fVolume":1230433,"label":"Dec 22, 20","volume":1230433,"updated":1609813001000,"open":17.91},
{"date":"2020-12-21","symbol":"DOC","subkey":"","fClose":17.6095,"uOpen":17.75,"uClose":17.84,"high":17.88,"fOpen":17.5206,"low":17.625,"changeOverTime":0.051266941661756105,"fHigh":17.649,"changePercent":-0.0138,"id":"HISTORICAL_PRICES","marketChangeOverTime":0.051266941661756105,"close":17.84,"key":"DOC","fLow":17.3973,"uHigh":17.88,"uVolume":1499658,"change":-0.25,"uLow":17.625,"fVolume":1499658,"label":"Dec 21, 20","volume":1499658,"updated":1609813063000,"open":17.75},
{"date":"2020-12-18","symbol":"DOC","subkey":"","fClose":17.7378,"uOpen":18.32,"uClose":17.97,"high":18.38,"fOpen":18.0833,"low":17.815,"changeOverTime":0.05892751915144373,"fHigh":18.1425,"changePercent":0.0073,"id":"HISTORICAL_PRICES","marketChangeOverTime":0.05892751915144373,"close":17.97,"key":"DOC","fLow":17.5848,"uHigh":18.38,"uVolume":4087325,"change":0.129999999999999,"uLow":17.815,"fVolume":4087325,"label":"Dec 18, 20","volume":4087325,"updated":1609812973000,"open":18.32},
{"date":"2020-12-17","symbol":"DOC","subkey":"","fClose":18.0734,"uOpen":18.32,"uClose":18.31,"high":18.38,"fOpen":18.0833,"low":18.105,"changeOverTime":0.07896287566293458,"fHigh":18.1425,"changePercent":0.0189,"id":"HISTORICAL_PRICES","marketChangeOverTime":0.07896287566293458,"close":18.31,"key":"DOC","fLow":17.8711,"uHigh":18.38,"uVolume":1702454,"change":0.33999999999999986,"uLow":18.105,"fVolume":1702454,"label":"Dec 17, 20","volume":1702454,"updated":1609813001000,"open":18.32},
{"date":"2020-12-16","symbol":"DOC","subkey":"","fClose":18.0438,"uOpen":18.34,"uClose":18.28,"high":18.46,"fOpen":18.103,"low":18.215,"changeOverTime":0.07719505008839142,"fHigh":18.2215,"changePercent":-0.0016,"id":"HISTORICAL_PRICES","marketChangeOverTime":0.07719505008839142,"close":18.28,"key":"DOC","fLow":17.9796,"uHigh":18.46,"uVolume":1851780,"change":-0.029999999999997584,"uLow":18.215,"fVolume":1851780,"label":"Dec 16, 20","volume":1851780,"updated":1609812976000,"open":18.34},
{"date":"2020-12-15","symbol":"DOC","subkey":"","fClose":18.0142,"uOpen":17.95,"uClose":18.25,"high":18.26,"fOpen":17.7181,"low":17.78,"changeOverTime":0.07542722451384803,"fHigh":18.0241,"changePercent":-0.0016,"id":"HISTORICAL_PRICES","marketChangeOverTime":0.07542722451384803,"close":18.25,"key":"DOC","fLow":17.5503,"uHigh":18.26,"uVolume":1895324,"change":-0.030000000000001137,"uLow":17.78,"fVolume":1895324,"label":"Dec 15, 20","volume":1895324,"updated":1609812965000,"open":17.95},
{"date":"2020-12-14","symbol":"DOC","subkey":"","fClose":17.649,"uOpen":18.02,"uClose":17.88,"high":18.17,"fOpen":17.7872,"low":17.86,"changeOverTime":0.0536240424278138,"fHigh":17.9352,"changePercent":-0.0203,"id":"HISTORICAL_PRICES","marketChangeOverTime":0.0536240424278138,"close":17.88,"key":"DOC","fLow":17.6292,"uHigh":18.17,"uVolume":2207861,"change":-0.370000000000001,"uLow":17.86,"fVolume":2207861,"label":"Dec 14, 20","volume":2207861,"updated":1609813035000,"open":18.02},
{"date":"2020-12-11","symbol":"DOC","subkey":"","fClose":17.8168,"uOpen":17.65,"uClose":18.05,"high":18.06,"fOpen":17.4219,"low":17.6436,"changeOverTime":0.06364172068355933,"fHigh":17.8266,"changePercent":0.0095,"id":"HISTORICAL_PRICES","marketChangeOverTime":0.06364172068355933,"close":18.05,"key":"DOC","fLow":17.4156,"uHigh":18.06,"uVolume":2828798,"change":0.1700000000000017,"uLow":17.6436,"fVolume":2828798,"label":"Dec 11, 20","volume":2828798,"updated":1609813001000,"open":17.65},
{"date":"2020-12-10","symbol":"DOC","subkey":"","fClose":17.5009,"uOpen":17.62,"uClose":17.73,"high":17.78,"fOpen":17.3923,"low":17.5,"changeOverTime":0.044784914555097324,"fHigh":17.5503,"changePercent":-0.0177,"id":"HISTORICAL_PRICES","marketChangeOverTime":0.044784914555097324,"close":17.73,"key":"DOC","fLow":17.2739,"uHigh":17.78,"uVolume":910156,"change":-0.3200000000000003,"uLow":17.5,"fVolume":910156,"label":"Dec 10, 20","volume":910156,"updated":1609813021000,"open":17.62},
{"date":"2020-12-09","symbol":"DOC","subkey":"","fClose":17.5009,"uOpen":17.83,"uClose":17.73,"high":17.93,"fOpen":17.5996,"low":17.42,"changeOverTime":0.044784914555097324,"fHigh":17.6983,"changePercent":0,"id":"HISTORICAL_PRICES","marketChangeOverTime":0.044784914555097324,"close":17.73,"key":"DOC","fLow":17.1949,"uHigh":17.93,"uVolume":1565489,"change":0,"uLow":17.42,"fVolume":1565489,"label":"Dec 9, 20","volume":1565489,"updated":1609812991000,"open":17.83},
{"date":"2020-12-08","symbol":"DOC","subkey":"","fClose":17.5996,"uOpen":17.76,"uClose":17.83,"high":17.88,"fOpen":17.5305,"low":17.672,"changeOverTime":0.05067766647024157,"fHigh":17.649,"changePercent":0.0056,"id":"HISTORICAL_PRICES","marketChangeOverTime":0.05067766647024157,"close":17.83,"key":"DOC","fLow":17.4437,"uHigh":17.88,"uVolume":1516911,"change":0.09999999999999787,"uLow":17.672,"fVolume":1516911,"label":"Dec 8, 20","volume":1516911,"updated":1609813050000,"open":17.76},
{"date":"2020-12-07","symbol":"DOC","subkey":"","fClose":17.6292,"uOpen":17.67,"uClose":17.86,"high":17.89,"fOpen":17.4417,"low":17.585,"changeOverTime":0.05244549204478495,"fHigh":17.6588,"changePercent":0.0017,"id":"HISTORICAL_PRICES","marketChangeOverTime":0.05244549204478495,"close":17.86,"key":"DOC","fLow":17.3578,"uHigh":17.89,"uVolume":1187264,"change":0.030000000000001137,"uLow":17.585,"fVolume":1187264,"label":"Dec 7, 20","volume":1187264,"updated":1609813011000,"open":17.67},
{"date":"2020-12-04","symbol":"DOC","subkey":"","fClose":17.4713,"uOpen":17.53,"uClose":17.7,"high":17.82,"fOpen":17.3035,"low":17.52,"changeOverTime":0.043017088980553946,"fHigh":17.5897,"changePercent":-0.009,"id":"HISTORICAL_PRICES","marketChangeOverTime":0.043017088980553946,"close":17.7,"key":"DOC","fLow":17.2936,"uHigh":17.82,"uVolume":1398553,"change":-0.16000000000000014,"uLow":17.52,"fVolume":1398553,"label":"Dec 4, 20","volume":1398553,"updated":1609812991000,"open":17.53},
{"date":"2020-12-03","symbol":"DOC","subkey":"","fClose":17.2936,"uOpen":17.51,"uClose":17.52,"high":17.72,"fOpen":17.2837,"low":17.44,"changeOverTime":0.03241013553329409,"fHigh":17.491,"changePercent":-0.0102,"id":"HISTORICAL_PRICES","marketChangeOverTime":0.03241013553329409,"close":17.52,"key":"DOC","fLow":17.2147,"uHigh":17.72,"uVolume":1227216,"change":-0.17999999999999972,"uLow":17.44,"fVolume":1227216,"label":"Dec 3, 20","volume":1227216,"updated":1609813011000,"open":17.51},
{"date":"2020-12-02","symbol":"DOC","subkey":"","fClose":17.2245,"uOpen":17.57,"uClose":17.45,"high":17.65,"fOpen":17.343,"low":17.29,"changeOverTime":0.028285209192693013,"fHigh":17.4219,"changePercent":-0.004,"id":"HISTORICAL_PRICES","marketChangeOverTime":0.028285209192693013,"close":17.45,"key":"DOC","fLow":17.0666,"uHigh":17.65,"uVolume":1799135,"change":-0.07000000000000028,"uLow":17.29,"fVolume":1799135,"label":"Dec 2, 20","volume":1799135,"updated":1609813001000,"open":17.57},
{"date":"2020-12-01","symbol":"DOC","subkey":"","fClose":17.3825,"uOpen":17.47,"uClose":17.61,"high":17.7,"fOpen":17.2443,"low":17.37,"changeOverTime":0.03771361225692402,"fHigh":17.4713,"changePercent":0.0092,"id":"HISTORICAL_PRICES","marketChangeOverTime":0.03771361225692402,"close":17.61,"key":"DOC","fLow":17.1456,"uHigh":17.7,"uVolume":1725314,"change":0.16000000000000014,"uLow":17.37,"fVolume":1725314,"label":"Dec 1, 20","volume":1725314,"updated":1609812976000,"open":17.47},
{"date":"2020-11-30","symbol":"DOC","subkey":"","fClose":17.1258,"uOpen":17.5,"uClose":17.35,"high":17.57,"fOpen":17.2739,"low":17.3,"changeOverTime":0.022392457277548766,"fHigh":17.343,"changePercent":-0.0148,"id":"HISTORICAL_PRICES","marketChangeOverTime":0.022392457277548766,"close":17.35,"key":"DOC","fLow":17.0765,"uHigh":17.57,"uVolume":1970874,"change":-0.259999999999998,"uLow":17.3,"fVolume":1970874,"label":"Nov 30, 20","volume":1970874,"updated":1609812976000,"open":17.5},
{"date":"2020-11-27","symbol":"DOC","subkey":"","fClose":17.3232,"uOpen":17.76,"uClose":17.55,"high":17.76,"fOpen":17.5305,"low":17.4,"changeOverTime":0.03417796110783747,"fHigh":17.5305,"changePercent":0.0115,"id":"HISTORICAL_PRICES","marketChangeOverTime":0.03417796110783747,"close":17.55,"key":"DOC","fLow":17.1752,"uHigh":17.76,"uVolume":657295,"change":0.1999999999999993,"uLow":17.4,"fVolume":657295,"label":"Nov 27, 20","volume":657295,"updated":1609813087000,"open":17.76},
{"date":"2020-11-25","symbol":"DOC","subkey":"","fClose":17.5404,"uOpen":17.88,"uClose":17.77,"high":17.91,"fOpen":17.649,"low":17.56,"changeOverTime":0.04714201532115502,"fHigh":17.6786,"changePercent":0.0125,"id":"HISTORICAL_PRICES","marketChangeOverTime":0.04714201532115502,"close":17.77,"key":"DOC","fLow":17.3331,"uHigh":17.91,"uVolume":1758202,"change":0.21999999999999886,"uLow":17.56,"fVolume":1758202,"label":"Nov 25, 20","volume":1758202,"updated":1609813030000,"open":17.88},
{"date":"2020-11-24","symbol":"DOC","subkey":"","fClose":17.6194,"uOpen":17.96,"uClose":17.85,"high":18.23,"fOpen":17.7279,"low":17.79,"changeOverTime":0.05185621685327063,"fHigh":17.9944,"changePercent":0.0045,"id":"HISTORICAL_PRICES","marketChangeOverTime":0.05185621685327063,"close":17.85,"key":"DOC","fLow":17.5601,"uHigh":18.23,"uVolume":2408897,"change":0.08000000000000185,"uLow":17.79,"fVolume":2408897,"label":"Nov 24, 20","volume":2408897,"updated":1609813011000,"open":17.96},
{"date":"2020-11-23","symbol":"DOC","subkey":"","fClose":17.5009,"uOpen":17.85,"uClose":17.73,"high":18.135,"fOpen":17.6194,"low":17.73,"changeOverTime":0.044784914555097324,"fHigh":17.9007,"changePercent":-0.0067,"id":"HISTORICAL_PRICES","marketChangeOverTime":0.044784914555097324,"close":17.73,"key":"DOC","fLow":17.5009,"uHigh":18.135,"uVolume":1436678,"change":-0.120000000000001,"uLow":17.73,"fVolume":1436678,"label":"Nov 23, 20","volume":1436678,"updated":1609812991000,"open":17.85},
{"date":"2020-11-20","symbol":"DOC","subkey":"","fClose":17.5009,"uOpen":17.91,"uClose":17.73,"high":17.95,"fOpen":17.6786,"low":17.62,"changeOverTime":0.044784914555097324,"fHigh":17.7181,"changePercent":0,"id":"HISTORICAL_PRICES","marketChangeOverTime":0.044784914555097324,"close":17.73,"key":"DOC","fLow":17.3923,"uHigh":17.95,"uVolume":1421316,"change":0,"uLow":17.62,"fVolume":1421316,"label":"Nov 20, 20","volume":1421316,"updated":1609813035000,"open":17.91},
{"date":"2020-11-19","symbol":"DOC","subkey":"","fClose":17.7477,"uOpen":17.86,"uClose":17.98,"high":18.035,"fOpen":17.6292,"low":17.68,"changeOverTime":0.05951679434295826,"fHigh":17.802,"changePercent":0.0141,"id":"HISTORICAL_PRICES","marketChangeOverTime":0.05951679434295826,"close":17.98,"key":"DOC","fLow":17.4516,"uHigh":18.035,"uVolume":1077894,"change":0.25,"uLow":17.68,"fVolume":1077894,"label":"Nov 19, 20","volume":1077894,"updated":1609813021000,"open":17.86},
{"date":"2020-11-18","symbol":"DOC","subkey":"","fClose":17.7279,"uOpen":18.34,"uClose":17.96,"high":18.445,"fOpen":18.103,"low":17.91,"changeOverTime":0.058338243959929405,"fHigh":18.2067,"changePercent":-0.0011,"id":"HISTORICAL_PRICES","marketChangeOverTime":0.058338243959929405,"close":17.96,"key":"DOC","fLow":17.6786,"uHigh":18.445,"uVolume":1618056,"change":-0.019999999999999574,"uLow":17.91,"fVolume":1618056,"label":"Nov 18, 20","volume":1618056,"updated":1609812961000,"open":18.34},
{"date":"2020-11-17","symbol":"DOC","subkey":"","fClose":18.0932,"uOpen":18.53,"uClose":18.33,"high":18.54,"fOpen":18.2906,"low":18.21,"changeOverTime":0.08014142604596344,"fHigh":18.3004,"changePercent":0.0206,"id":"HISTORICAL_PRICES","marketChangeOverTime":0.08014142604596344,"close":18.33,"key":"DOC","fLow":17.9747,"uHigh":18.54,"uVolume":2235421,"change":0.36999999999999744,"uLow":18.21,"fVolume":2235421,"label":"Nov 17, 20","volume":2235421,"updated":1609813011000,"open":18.53},
{"date":"2020-11-16","symbol":"DOC","subkey":"","fClose":18.4386,"uOpen":19.06,"uClose":18.68,"high":19.21,"fOpen":18.8137,"low":18.535,"changeOverTime":0.10076605774896882,"fHigh":18.9618,"changePercent":0.0191,"id":"HISTORICAL_PRICES","marketChangeOverTime":0.10076605774896882,"close":18.68,"key":"DOC","fLow":18.2955,"uHigh":19.21,"uVolume":2078197,"change":0.3500000000000014,"uLow":18.535,"fVolume":2078197,"label":"Nov 16, 20","volume":2078197,"updated":1609813001000,"open":19.06},
{"date":"2020-11-13","symbol":"DOC","subkey":"","fClose":18.4682,"uOpen":18.5,"uClose":18.71,"high":18.75,"fOpen":18.261,"low":18.49,"changeOverTime":0.10253388332351221,"fHigh":18.5077,"changePercent":0.0016,"id":"HISTORICAL_PRICES","marketChangeOverTime":0.10253388332351221,"close":18.71,"key":"DOC","fLow":18.2511,"uHigh":18.75,"uVolume":2104810,"change":0.030000000000001137,"uLow":18.49,"fVolume":2104810,"label":"Nov 13, 20","volume":2104810,"updated":1609813030000,"open":18.5},
{"date":"2020-11-12","symbol":"DOC","subkey":"","fClose":18.1919,"uOpen":18.44,"uClose":18.43,"high":18.56,"fOpen":18.2017,"low":18.09,"changeOverTime":0.08603417796110789,"fHigh":18.3202,"changePercent":-0.015,"id":"HISTORICAL_PRICES","marketChangeOverTime":0.08603417796110789,"close":18.43,"key":"DOC","fLow":17.8563,"uHigh":18.56,"uVolume":2472226,"change":-0.28000000000000114,"uLow":18.09,"fVolume":2472226,"label":"Nov 12, 20","volume":2472226,"updated":1609813035000,"open":18.44},
{"date":"2020-11-11","symbol":"DOC","subkey":"","fClose":18.3794,"uOpen":18.44,"uClose":18.62,"high":18.63,"fOpen":18.2017,"low":18.065,"changeOverTime":0.09723040659988227,"fHigh":18.3893,"changePercent":0.0103,"id":"HISTORICAL_PRICES","marketChangeOverTime":0.09723040659988227,"close":18.62,"key":"DOC","fLow":17.8316,"uHigh":18.63,"uVolume":2497413,"change":0.19000000000000128,"uLow":18.065,"fVolume":2497413,"label":"Nov 11, 20","volume":2497413,"updated":1609813011000,"open":18.44},
{"date":"2020-11-10","symbol":"DOC","subkey":"","fClose":18.3301,"uOpen":17.95,"uClose":18.57,"high":18.59,"fOpen":17.7181,"low":17.76,"changeOverTime":0.09428403064231004,"fHigh":18.3498,"changePercent":-0.0027,"id":"HISTORICAL_PRICES","marketChangeOverTime":0.09428403064231004,"close":18.57,"key":"DOC","fLow":17.5305,"uHigh":18.59,"uVolume":2245534,"change":-0.05000000000000071,"uLow":17.76,"fVolume":2245534,"label":"Nov 10, 20","volume":2245534,"updated":1609813001000,"open":17.95},
{"date":"2020-11-09","symbol":"DOC","subkey":"","fClose":17.5897,"uOpen":19,"uClose":17.82,"high":20.13,"fOpen":18.7545,"low":17.8,"changeOverTime":0.05008839127872725,"fHigh":19.8699,"changePercent":-0.0404,"id":"HISTORICAL_PRICES","marketChangeOverTime":0.05008839127872725,"close":17.82,"key":"DOC","fLow":17.57,"uHigh":20.13,"uVolume":3230084,"change":-0.75,"uLow":17.8,"fVolume":3230084,"label":"Nov 9, 20","volume":3230084,"updated":1609812973000,"open":19},
{"date":"2020-11-06","symbol":"DOC","subkey":"","fClose":17.5108,"uOpen":18.01,"uClose":17.74,"high":18.24,"fOpen":17.7773,"low":17.605,"changeOverTime":0.04537418974661164,"fHigh":18.0043,"changePercent":-0.0045,"id":"HISTORICAL_PRICES","marketChangeOverTime":0.04537418974661164,"close":17.74,"key":"DOC","fLow":17.3775,"uHigh":18.24,"uVolume":1250534,"change":-0.08000000000000185,"uLow":17.605,"fVolume":1250534,"label":"Nov 6, 20","volume":1250534,"updated":1609813035000,"open":18.01},
{"date":"2020-11-05","symbol":"DOC","subkey":"","fClose":17.7773,"uOpen":18,"uClose":18.01,"high":18.2,"fOpen":17.7674,"low":17.85,"changeOverTime":0.061284619917501636,"fHigh":17.9648,"changePercent":0.0152,"id":"HISTORICAL_PRICES","marketChangeOverTime":0.061284619917501636,"close":18.01,"key":"DOC","fLow":17.6194,"uHigh":18.2,"uVolume":1049099,"change":0.2700000000000031,"uLow":17.85,"fVolume":1049099,"label":"Nov 5, 20","volume":1049099,"updated":1609812984000,"open":18},
{"date":"2020-11-04","symbol":"DOC","subkey":"","fClose":17.7082,"uOpen":17.73,"uClose":17.94,"high":18.075,"fOpen":17.5009,"low":17.53,"changeOverTime":0.05715969357690056,"fHigh":17.8414,"changePercent":-0.0039,"id":"HISTORICAL_PRICES","marketChangeOverTime":0.05715969357690056,"close":17.94,"key":"DOC","fLow":17.3035,"uHigh":18.075,"uVolume":1408108,"change":-0.07000000000000028,"uLow":17.53,"fVolume":1408108,"label":"Nov 4, 20","volume":1408108,"updated":1609813001000,"open":17.73},
{"date":"2020-11-03","symbol":"DOC","subkey":"","fClose":17.5601,"uOpen":17.44,"uClose":17.79,"high":17.88,"fOpen":17.2147,"low":17.17,"changeOverTime":0.048320565704183874,"fHigh":17.649,"changePercent":-0.0084,"id":"HISTORICAL_PRICES","marketChangeOverTime":0.048320565704183874,"close":17.79,"key":"DOC","fLow":16.9481,"uHigh":17.88,"uVolume":1692676,"change":-0.15000000000000213,"uLow":17.17,"fVolume":1692676,"label":"Nov 3, 20","volume":1692676,"updated":1609813021000,"open":17.44},
{"date":"2020-11-02","symbol":"DOC","subkey":"","fClose":16.9481,"uOpen":16.97,"uClose":17.17,"high":17.17,"fOpen":16.7507,"low":16.78,"changeOverTime":0.011785503830288913,"fHigh":16.9481,"changePercent":-0.0349,"id":"HISTORICAL_PRICES","marketChangeOverTime":0.011785503830288913,"close":17.17,"key":"DOC","fLow":16.5632,"uHigh":17.17,"uVolume":1946340,"change":-0.6199999999999974,"uLow":16.78,"fVolume":1946340,"label":"Nov 2, 20","volume":1946340,"updated":1609812965000,"open":16.97},
{"date":"2020-10-30","symbol":"DOC","subkey":"","fClose":16.6421,"uOpen":16.86,"uClose":16.86,"high":16.96,"fOpen":16.6421,"low":16.6,"changeOverTime":-0.006482027106658777,"fHigh":16.7409,"changePercent":-0.0181,"id":"HISTORICAL_PRICES","marketChangeOverTime":-0.006482027106658777,"close":16.86,"key":"DOC","fLow":16.3855,"uHigh":16.96,"uVolume":1587459,"change":-0.3100000000000023,"uLow":16.6,"fVolume":1587459,"label":"Oct 30, 20","volume":1587459,"updated":1609812965000,"open":16.86},
{"date":"2020-10-29","symbol":"DOC","subkey":"","fClose":16.7112,"uOpen":16.69,"uClose":16.93,"high":16.98,"fOpen":16.4743,"low":16.475,"changeOverTime":-0.002357100766057699,"fHigh":16.7606,"changePercent":0.0042,"id":"HISTORICAL_PRICES","marketChangeOverTime":-0.002357100766057699,"close":16.93,"key":"DOC","fLow":16.2621,"uHigh":16.98,"uVolume":1866275,"change":0.07000000000000028,"uLow":16.475,"fVolume":1866275,"label":"Oct 29, 20","volume":1866275,"updated":1609813021000,"open":16.69},
{"date":"2020-10-28","symbol":"DOC","subkey":"","fClose":16.5434,"uOpen":17.04,"uClose":16.76,"high":17.18,"fOpen":16.8198,"low":16.6,"changeOverTime":-0.012374779021803024,"fHigh":16.958,"changePercent":-0.01,"id":"HISTORICAL_PRICES","marketChangeOverTime":-0.012374779021803024,"close":16.76,"key":"DOC","fLow":16.3855,"uHigh":17.18,"uVolume":1946786,"change":-0.16999999999999815,"uLow":16.6,"fVolume":1946786,"label":"Oct 28, 20","volume":1946786,"updated":1609813030000,"open":17.04},
{"date":"2020-10-27","symbol":"DOC","subkey":"","fClose":17.1061,"uOpen":17.63,"uClose":17.33,"high":17.76,"fOpen":17.4022,"low":17.31,"changeOverTime":0.02121390689451971,"fHigh":17.5305,"changePercent":0.034,"id":"HISTORICAL_PRICES","marketChangeOverTime":0.02121390689451971,"close":17.33,"key":"DOC","fLow":17.0863,"uHigh":17.76,"uVolume":1338745,"change":0.5699999999999967,"uLow":17.31,"fVolume":1338745,"label":"Oct 27, 20","volume":1338745,"updated":1609812976000,"open":17.63},
{"date":"2020-10-26","symbol":"DOC","subkey":"","fClose":17.4022,"uOpen":17.79,"uClose":17.63,"high":17.81,"fOpen":17.5601,"low":17.45,"changeOverTime":0.03889216263995287,"fHigh":17.5799,"changePercent":0.0173,"id":"HISTORICAL_PRICES","marketChangeOverTime":0.03889216263995287,"close":17.63,"key":"DOC","fLow":17.2245,"uHigh":17.81,"uVolume":1201691,"change":0.3000000000000007,"uLow":17.45,"fVolume":1201691,"label":"Oct 26, 20","volume":1201691,"updated":1609813001000,"open":17.79},
{"date":"2020-10-23","symbol":"DOC","subkey":"","fClose":17.6786,"uOpen":18,"uClose":17.91,"high":18.06,"fOpen":17.7674,"low":17.705,"changeOverTime":0.05539186800235718,"fHigh":17.8266,"changePercent":0.0159,"id":"HISTORICAL_PRICES","marketChangeOverTime":0.05539186800235718,"close":17.91,"key":"DOC","fLow":17.4762,"uHigh":18.06,"uVolume":1044826,"change":0.28000000000000114,"uLow":17.705,"fVolume":1044826,"label":"Oct 23, 20","volume":1044826,"updated":1609812975000,"open":18},
{"date":"2020-10-22","symbol":"DOC","subkey":"","fClose":17.649,"uOpen":17.43,"uClose":17.88,"high":17.91,"fOpen":17.2048,"low":17.43,"changeOverTime":0.0536240424278138,"fHigh":17.6786,"changePercent":-0.0017,"id":"HISTORICAL_PRICES","marketChangeOverTime":0.0536240424278138,"close":17.88,"key":"DOC","fLow":17.2048,"uHigh":17.91,"uVolume":1189383,"change":-0.030000000000001137,"uLow":17.43,"fVolume":1189383,"label":"Oct 22, 20","volume":1189383,"updated":1609813087000,"open":17.43},
{"date":"2020-10-21","symbol":"DOC","subkey":"","fClose":17.2541,"uOpen":17.54,"uClose":17.48,"high":17.56,"fOpen":17.3134,"low":17.28,"changeOverTime":0.030053034767236392,"fHigh":17.3331,"changePercent":-0.0224,"id":"HISTORICAL_PRICES","marketChangeOverTime":0.030053034767236392,"close":17.48,"key":"DOC","fLow":17.0567,"uHigh":17.56,"uVolume":1416673,"change":-0.3999999999999986,"uLow":17.28,"fVolume":1416673,"label":"Oct 21, 20","volume":1416673,"updated":1609813063000,"open":17.54},
{"date":"2020-10-20","symbol":"DOC","subkey":"","fClose":17.343,"uOpen":17.63,"uClose":17.57,"high":17.74,"fOpen":17.4022,"low":17.49,"changeOverTime":0.03535651149086632,"fHigh":17.5108,"changePercent":0.0051,"id":"HISTORICAL_PRICES","marketChangeOverTime":0.03535651149086632,"close":17.57,"key":"DOC","fLow":17.264,"uHigh":17.74,"uVolume":908666,"change":0.08999999999999986,"uLow":17.49,"fVolume":908666,"label":"Oct 20, 20","volume":908666,"updated":1609812965000,"open":17.63},
{"date":"2020-10-19","symbol":"DOC","subkey":"","fClose":17.2739,"uOpen":17.99,"uClose":17.5,"high":17.99,"fOpen":17.7575,"low":17.46,"changeOverTime":0.031231585150265244,"fHigh":17.7575,"changePercent":-0.004,"id":"HISTORICAL_PRICES","marketChangeOverTime":0.031231585150265244,"close":17.5,"key":"DOC","fLow":17.2344,"uHigh":17.99,"uVolume":1617281,"change":-0.07000000000000028,"uLow":17.46,"fVolume":1617281,"label":"Oct 19, 20","volume":1617281,"updated":1609812961000,"open":17.99},
{"date":"2020-10-16","symbol":"DOC","subkey":"","fClose":17.5601,"uOpen":17.95,"uClose":17.79,"high":18.08,"fOpen":17.7181,"low":17.66,"changeOverTime":0.048320565704183874,"fHigh":17.8464,"changePercent":0.0166,"id":"HISTORICAL_PRICES","marketChangeOverTime":0.048320565704183874,"close":17.79,"key":"DOC","fLow":17.4318,"uHigh":18.08,"uVolume":1110246,"change":0.28999999999999915,"uLow":17.66,"fVolume":1110246,"label":"Oct 16, 20","volume":1110246,"updated":1609813012000,"open":17.95},
{"date":"2020-10-15","symbol":"DOC","subkey":"","fClose":17.8563,"uOpen":17.8,"uClose":18.09,"high":18.26,"fOpen":17.57,"low":17.73,"changeOverTime":0.06599882144961704,"fHigh":18.0241,"changePercent":0.0169,"id":"HISTORICAL_PRICES","marketChangeOverTime":0.06599882144961704,"close":18.09,"key":"DOC","fLow":17.5009,"uHigh":18.26,"uVolume":864407,"change":0.3000000000000007,"uLow":17.73,"fVolume":864407,"label":"Oct 15, 20","volume":864407,"updated":1609812965000,"open":17.8},
{"date":"2020-10-14","symbol":"DOC","subkey":"","fClose":17.6194,"uOpen":18.22,"uClose":17.85,"high":18.235,"fOpen":17.9846,"low":17.84,"changeOverTime":0.05185621685327063,"fHigh":17.9994,"changePercent":-0.0133,"id":"HISTORICAL_PRICES","marketChangeOverTime":0.05185621685327063,"close":17.85,"key":"DOC","fLow":17.6095,"uHigh":18.235,"uVolume":892568,"change":-0.23999999999999844,"uLow":17.84,"fVolume":892568,"label":"Oct 14, 20","volume":892568,"updated":1609812965000,"open":18.22},
{"date":"2020-10-13","symbol":"DOC","subkey":"","fClose":18.0241,"uOpen":18.32,"uClose":18.26,"high":18.41,"fOpen":18.0833,"low":18.05,"changeOverTime":0.07601649970536258,"fHigh":18.1721,"changePercent":0.023,"id":"HISTORICAL_PRICES","marketChangeOverTime":0.07601649970536258,"close":18.26,"key":"DOC","fLow":17.8168,"uHigh":18.41,"uVolume":884862,"change":0.41000000000000014,"uLow":18.05,"fVolume":884862,"label":"Oct 13, 20","volume":884862,"updated":1609813012000,"open":18.32},
{"date":"2020-10-12","symbol":"DOC","subkey":"","fClose":18.182,"uOpen":18.24,"uClose":18.42,"high":18.495,"fOpen":18.0043,"low":18.14,"changeOverTime":0.08544490276959357,"fHigh":18.256,"changePercent":0.0088,"id":"HISTORICAL_PRICES","marketChangeOverTime":0.08544490276959357,"close":18.42,"key":"DOC","fLow":17.9056,"uHigh":18.495,"uVolume":1733429,"change":0.16000000000000014,"uLow":18.14,"fVolume":1733429,"label":"Oct 12, 20","volume":1733429,"updated":1609812991000,"open":18.24},
{"date":"2020-10-09","symbol":"DOC","subkey":"","fClose":18.0043,"uOpen":18.67,"uClose":18.24,"high":18.67,"fOpen":18.4288,"low":18.22,"changeOverTime":0.07483794932233351,"fHigh":18.4288,"changePercent":-0.0098,"id":"HISTORICAL_PRICES","marketChangeOverTime":0.07483794932233351,"close":18.24,"key":"DOC","fLow":17.9846,"uHigh":18.67,"uVolume":1021375,"change":-0.18000000000000327,"uLow":18.22,"fVolume":1021375,"label":"Oct 9, 20","volume":1021375,"updated":1609812984000,"open":18.67}]