[{"date":"2021-01-08","symbol":"HCA","subkey":"","fClose":172.28,"uOpen":174,"uClose":172.28,"high":174.55,"fOpen":174,"low":169.58,"changeOverTime":0,"fHigh":174.55,"changePercent":0,"id":"HISTORICAL_PRICES","marketChangeOverTime":0,"close":172.28,"key":"HCA","fLow":169.58,"uHigh":174.55,"uVolume":1063595,"change":0,"uLow":169.58,"fVolume":1063595,"label":"Jan 8, 21","volume":1063595,"updated":1610158570000,"open":174},
{"date":"2021-01-07","symbol":"HCA","subkey":"","fClose":173.6,"uOpen":171.04,"uClose":173.6,"high":174.37,"fOpen":171.04,"low":171.04,"changeOverTime":0.0076619456698397564,"fHigh":174.37,"changePercent":0.0077,"id":"HISTORICAL_PRICES","marketChangeOverTime":0.0076619456698397564,"close":173.6,"key":"HCA","fLow":171.04,"uHigh":174.37,"uVolume":2094117,"change":1.3199999999999932,"uLow":171.04,"fVolume":2094117,"label":"Jan 7, 21","volume":2094117,"updated":1610072170000,"open":171.04},
{"date":"2021-01-05","symbol":"HCA","subkey":"","fClose":165.01,"uOpen":163.11,"uClose":165.01,"high":166.74,"fOpen":163.11,"low":162.22,"changeOverTime":-0.042198746227072266,"fHigh":166.74,"changePercent":-0.0495,"id":"HISTORICAL_PRICES","marketChangeOverTime":-0.042198746227072266,"close":165.01,"key":"HCA","fLow":162.22,"uHigh":166.74,"uVolume":1142263,"change":-8.590000000000003,"uLow":162.22,"fVolume":1142263,"label":"Jan 5, 21","volume":1142263,"updated":1609897695000,"open":163.11},
{"date":"2021-01-04","symbol":"HCA","subkey":"","fClose":163.64,"uOpen":163.37,"uClose":163.64,"high":164.94,"fOpen":163.37,"low":158.37,"changeOverTime":-0.050150917111678746,"fHigh":164.94,"changePercent":-0.0083,"id":"HISTORICAL_PRICES","marketChangeOverTime":-0.050150917111678746,"close":163.64,"key":"HCA","fLow":158.37,"uHigh":164.94,"uVolume":1616978,"change":-1.3700000000000045,"uLow":158.37,"fVolume":1616978,"label":"Jan 4, 21","volume":1616978,"updated":1609812011000,"open":163.37},
{"date":"2020-12-31","symbol":"HCA","subkey":"","fClose":164.46,"uOpen":163.07,"uClose":164.46,"high":165,"fOpen":163.07,"low":161.78,"changeOverTime":-0.04539122358950542,"fHigh":165,"changePercent":0.005,"id":"HISTORICAL_PRICES","marketChangeOverTime":-0.04539122358950542,"close":164.46,"key":"HCA","fLow":161.78,"uHigh":165,"uVolume":958160,"change":0.8200000000000216,"uLow":161.78,"fVolume":958160,"label":"Dec 31, 20","volume":958160,"updated":1609468335000,"open":163.07},
{"date":"2020-12-30","symbol":"HCA","subkey":"","fClose":162.35,"uOpen":163.28,"uClose":162.35,"high":163.92,"fOpen":163.28,"low":161.54,"changeOverTime":-0.057638727652658504,"fHigh":163.92,"changePercent":-0.0128,"id":"HISTORICAL_PRICES","marketChangeOverTime":-0.057638727652658504,"close":162.35,"key":"HCA","fLow":161.54,"uHigh":163.92,"uVolume":879449,"change":-2.1100000000000136,"uLow":161.54,"fVolume":879449,"label":"Dec 30, 20","volume":879449,"updated":1609381958000,"open":163.28},
{"date":"2020-12-29","symbol":"HCA","subkey":"","fClose":163.5622,"uOpen":164.23,"uClose":163.83,"high":165.03,"fOpen":163.9615,"low":162.53,"changeOverTime":-0.04904806129556529,"fHigh":164.7602,"changePercent":0.0091,"id":"HISTORICAL_PRICES","marketChangeOverTime":-0.04904806129556529,"close":163.83,"key":"HCA","fLow":162.2643,"uHigh":165.03,"uVolume":915492,"change":1.4800000000000182,"uLow":162.53,"fVolume":915492,"label":"Dec 29, 20","volume":915492,"updated":1609377619000,"open":164.23},
{"date":"2020-12-28","symbol":"HCA","subkey":"","fClose":163.7319,"uOpen":165.56,"uClose":164,"high":165.65,"fOpen":165.2894,"low":163.19,"changeOverTime":-0.04806129556535872,"fHigh":165.3792,"changePercent":0.001,"id":"HISTORICAL_PRICES","marketChangeOverTime":-0.04806129556535872,"close":164,"key":"HCA","fLow":162.9232,"uHigh":165.65,"uVolume":906634,"change":0.1699999999999875,"uLow":163.19,"fVolume":906634,"label":"Dec 28, 20","volume":906634,"updated":1609377649000,"open":165.56},
{"date":"2020-12-24","symbol":"HCA","subkey":"","fClose":163.9715,"uOpen":166.87,"uClose":164.24,"high":166.87,"fOpen":166.5972,"low":164.08,"changeOverTime":-0.04666821453447871,"fHigh":166.5972,"changePercent":0.0015,"id":"HISTORICAL_PRICES","marketChangeOverTime":-0.04666821453447871,"close":164.24,"key":"HCA","fLow":163.8118,"uHigh":166.87,"uVolume":288897,"change":0.2400000000000091,"uLow":164.08,"fVolume":288897,"label":"Dec 24, 20","volume":288897,"updated":1609377586000,"open":166.87},
{"date":"2020-12-23","symbol":"HCA","subkey":"","fClose":165.5889,"uOpen":164.64,"uClose":165.86,"high":166.86,"fOpen":164.3709,"low":164.42,"changeOverTime":-0.03726491757603893,"fHigh":166.5872,"changePercent":0.0099,"id":"HISTORICAL_PRICES","marketChangeOverTime":-0.03726491757603893,"close":165.86,"key":"HCA","fLow":164.1512,"uHigh":166.86,"uVolume":1904836,"change":1.6200000000000045,"uLow":164.42,"fVolume":1904836,"label":"Dec 23, 20","volume":1904836,"updated":1609377649000,"open":164.64},
{"date":"2020-12-22","symbol":"HCA","subkey":"","fClose":163.0031,"uOpen":163.5,"uClose":163.27,"high":164.42,"fOpen":163.2327,"low":161.88,"changeOverTime":-0.05229858370095188,"fHigh":164.1512,"changePercent":-0.0156,"id":"HISTORICAL_PRICES","marketChangeOverTime":-0.05229858370095188,"close":163.27,"key":"HCA","fLow":161.6154,"uHigh":164.42,"uVolume":1813119,"change":-2.5900000000000034,"uLow":161.88,"fVolume":1813119,"label":"Dec 22, 20","volume":1813119,"updated":1609377444000,"open":163.5},
{"date":"2020-12-21","symbol":"HCA","subkey":"","fClose":162.8234,"uOpen":161.19,"uClose":163.09,"high":164.34,"fOpen":160.9265,"low":158.89,"changeOverTime":-0.0533433944741119,"fHigh":164.0714,"changePercent":-0.0011,"id":"HISTORICAL_PRICES","marketChangeOverTime":-0.0533433944741119,"close":163.09,"key":"HCA","fLow":158.6303,"uHigh":164.34,"uVolume":1831138,"change":-0.18000000000000682,"uLow":158.89,"fVolume":1831138,"label":"Dec 21, 20","volume":1831138,"updated":1609377648000,"open":161.19},
{"date":"2020-12-18","symbol":"HCA","subkey":"","fClose":164.0714,"uOpen":165.19,"uClose":164.34,"high":165.98,"fOpen":164.92,"low":163.21,"changeOverTime":-0.046087764104945424,"fHigh":165.7087,"changePercent":0.0077,"id":"HISTORICAL_PRICES","marketChangeOverTime":-0.046087764104945424,"close":164.34,"key":"HCA","fLow":162.9432,"uHigh":165.98,"uVolume":3119898,"change":1.25,"uLow":163.21,"fVolume":3119898,"label":"Dec 18, 20","volume":3119898,"updated":1609377519000,"open":165.19},
{"date":"2020-12-17","symbol":"HCA","subkey":"","fClose":164.4807,"uOpen":162.78,"uClose":164.75,"high":165.74,"fOpen":162.5139,"low":162.61,"changeOverTime":-0.04370791734385884,"fHigh":165.4691,"changePercent":0.0025,"id":"HISTORICAL_PRICES","marketChangeOverTime":-0.04370791734385884,"close":164.75,"key":"HCA","fLow":162.3442,"uHigh":165.74,"uVolume":1371602,"change":0.4099999999999966,"uLow":162.61,"fVolume":1371602,"label":"Dec 17, 20","volume":1371602,"updated":1609377444000,"open":162.78},
{"date":"2020-12-16","symbol":"HCA","subkey":"","fClose":161.2959,"uOpen":160.68,"uClose":161.56,"high":162.55,"fOpen":160.4173,"low":159.67,"changeOverTime":-0.06222428604597167,"fHigh":162.2843,"changePercent":-0.0194,"id":"HISTORICAL_PRICES","marketChangeOverTime":-0.06222428604597167,"close":161.56,"key":"HCA","fLow":159.409,"uHigh":162.55,"uVolume":1107060,"change":-3.1899999999999977,"uLow":159.67,"fVolume":1107060,"label":"Dec 16, 20","volume":1107060,"updated":1609377586000,"open":160.68},
{"date":"2020-12-15","symbol":"HCA","subkey":"","fClose":160.6869,"uOpen":163.13,"uClose":160.95,"high":163.44,"fOpen":162.8633,"low":159.25,"changeOverTime":-0.06576503366612499,"fHigh":163.1728,"changePercent":-0.0038,"id":"HISTORICAL_PRICES","marketChangeOverTime":-0.06576503366612499,"close":160.95,"key":"HCA","fLow":158.9897,"uHigh":163.44,"uVolume":1625709,"change":-0.6100000000000136,"uLow":159.25,"fVolume":1625709,"label":"Dec 15, 20","volume":1625709,"updated":1609377634000,"open":163.13},
{"date":"2020-12-14","symbol":"HCA","subkey":"","fClose":160.5971,"uOpen":163.87,"uClose":160.86,"high":165.24,"fOpen":163.6021,"low":159.715,"changeOverTime":-0.06628743905270483,"fHigh":164.9699,"changePercent":-0.0006,"id":"HISTORICAL_PRICES","marketChangeOverTime":-0.06628743905270483,"close":160.86,"key":"HCA","fLow":159.4539,"uHigh":165.24,"uVolume":1833503,"change":-0.08999999999997499,"uLow":159.715,"fVolume":1833503,"label":"Dec 14, 20","volume":1833503,"updated":1609377631000,"open":163.87},
{"date":"2020-12-11","symbol":"HCA","subkey":"","fClose":157.3124,"uOpen":160.32,"uClose":157.57,"high":161.44,"fOpen":160.0579,"low":156.67,"changeOverTime":-0.08538425818435111,"fHigh":161.1761,"changePercent":-0.0205,"id":"HISTORICAL_PRICES","marketChangeOverTime":-0.08538425818435111,"close":157.57,"key":"HCA","fLow":156.4139,"uHigh":161.44,"uVolume":1153183,"change":-3.2900000000000205,"uLow":156.67,"fVolume":1153183,"label":"Dec 11, 20","volume":1153183,"updated":1609377644000,"open":160.32},
{"date":"2020-12-10","symbol":"HCA","subkey":"","fClose":161.5255,"uOpen":159.39,"uClose":161.79,"high":164.22,"fOpen":159.1295,"low":159.39,"changeOverTime":-0.060889250058045095,"fHigh":163.9516,"changePercent":0.0268,"id":"HISTORICAL_PRICES","marketChangeOverTime":-0.060889250058045095,"close":161.79,"key":"HCA","fLow":159.1295,"uHigh":164.22,"uVolume":1401555,"change":4.219999999999999,"uLow":159.39,"fVolume":1401555,"label":"Dec 10, 20","volume":1401555,"updated":1609377613000,"open":159.39},
{"date":"2020-12-09","symbol":"HCA","subkey":"","fClose":159.6686,"uOpen":158.86,"uClose":159.93,"high":161.415,"fOpen":158.6003,"low":158.27,"changeOverTime":-0.07168562804736472,"fHigh":161.1511,"changePercent":-0.0115,"id":"HISTORICAL_PRICES","marketChangeOverTime":-0.07168562804736472,"close":159.93,"key":"HCA","fLow":158.0113,"uHigh":161.415,"uVolume":1531888,"change":-1.8599999999999852,"uLow":158.27,"fVolume":1531888,"label":"Dec 9, 20","volume":1531888,"updated":1609377483000,"open":158.86},
{"date":"2020-12-08","symbol":"HCA","subkey":"","fClose":158.9298,"uOpen":155.13,"uClose":159.19,"high":159.65,"fOpen":154.8764,"low":155,"changeOverTime":-0.07598096122591133,"fHigh":159.389,"changePercent":-0.0046,"id":"HISTORICAL_PRICES","marketChangeOverTime":-0.07598096122591133,"close":159.19,"key":"HCA","fLow":154.7466,"uHigh":159.65,"uVolume":1367493,"change":-0.7400000000000091,"uLow":155,"fVolume":1367493,"label":"Dec 8, 20","volume":1367493,"updated":1609377609000,"open":155.13},
{"date":"2020-12-07","symbol":"HCA","subkey":"","fClose":155.116,"uOpen":157.15,"uClose":155.37,"high":157.68,"fOpen":156.8931,"low":153.75,"changeOverTime":-0.09815416763408402,"fHigh":157.4223,"changePercent":-0.024,"id":"HISTORICAL_PRICES","marketChangeOverTime":-0.09815416763408402,"close":155.37,"key":"HCA","fLow":153.4987,"uHigh":157.68,"uVolume":1043511,"change":-3.819999999999993,"uLow":153.75,"fVolume":1043511,"label":"Dec 7, 20","volume":1043511,"updated":1609377590000,"open":157.15},
{"date":"2020-12-04","symbol":"HCA","subkey":"","fClose":157.4223,"uOpen":153.65,"uClose":157.68,"high":158.21,"fOpen":153.3988,"low":152.58,"changeOverTime":-0.08474576271186438,"fHigh":157.9514,"changePercent":0.0149,"id":"HISTORICAL_PRICES","marketChangeOverTime":-0.08474576271186438,"close":157.68,"key":"HCA","fLow":152.3306,"uHigh":158.21,"uVolume":1447115,"change":2.3100000000000023,"uLow":152.58,"fVolume":1447115,"label":"Dec 4, 20","volume":1447115,"updated":1609377483000,"open":153.65},
{"date":"2020-12-03","symbol":"HCA","subkey":"","fClose":152.5003,"uOpen":153.25,"uClose":152.75,"high":154.07,"fOpen":152.9995,"low":151.934,"changeOverTime":-0.11336196888785699,"fHigh":153.8182,"changePercent":-0.0313,"id":"HISTORICAL_PRICES","marketChangeOverTime":-0.11336196888785699,"close":152.75,"key":"HCA","fLow":151.6856,"uHigh":154.07,"uVolume":906424,"change":-4.930000000000007,"uLow":151.934,"fVolume":906424,"label":"Dec 3, 20","volume":906424,"updated":1609377590000,"open":153.25},
{"date":"2020-12-02","symbol":"HCA","subkey":"","fClose":152.3506,"uOpen":150.46,"uClose":152.6,"high":153.37,"fOpen":150.2141,"low":149.75,"changeOverTime":-0.114232644532157,"fHigh":153.1193,"changePercent":-0.001,"id":"HISTORICAL_PRICES","marketChangeOverTime":-0.114232644532157,"close":152.6,"key":"HCA","fLow":149.5052,"uHigh":153.37,"uVolume":839192,"change":-0.15000000000000568,"uLow":149.75,"fVolume":839192,"label":"Dec 2, 20","volume":839192,"updated":1609377444000,"open":150.46},
{"date":"2020-12-01","symbol":"HCA","subkey":"","fClose":151.6617,"uOpen":152.64,"uClose":151.91,"high":153.7,"fOpen":152.3905,"low":151.12,"changeOverTime":-0.11823775249593688,"fHigh":153.4488,"changePercent":-0.0045,"id":"HISTORICAL_PRICES","marketChangeOverTime":-0.11823775249593688,"close":151.91,"key":"HCA","fLow":150.873,"uHigh":153.7,"uVolume":880584,"change":-0.6899999999999977,"uLow":151.12,"fVolume":880584,"label":"Dec 1, 20","volume":880584,"updated":1609377586000,"open":152.64},
{"date":"2020-11-30","symbol":"HCA","subkey":"","fClose":149.8646,"uOpen":152.46,"uClose":150.11,"high":152.46,"fOpen":152.2108,"low":148.92,"changeOverTime":-0.1286858602275365,"fHigh":152.2108,"changePercent":-0.0118,"id":"HISTORICAL_PRICES","marketChangeOverTime":-0.1286858602275365,"close":150.11,"key":"HCA","fLow":148.6766,"uHigh":152.46,"uVolume":1846260,"change":-1.799999999999983,"uLow":148.92,"fVolume":1846260,"label":"Nov 30, 20","volume":1846260,"updated":1609377586000,"open":152.46},
{"date":"2020-11-27","symbol":"HCA","subkey":"","fClose":152.7998,"uOpen":153.5,"uClose":153.05,"high":155,"fOpen":153.2491,"low":152.31,"changeOverTime":-0.11162061759925697,"fHigh":154.7466,"changePercent":0.0196,"id":"HISTORICAL_PRICES","marketChangeOverTime":-0.11162061759925697,"close":153.05,"key":"HCA","fLow":152.061,"uHigh":155,"uVolume":753487,"change":2.9399999999999977,"uLow":152.31,"fVolume":753487,"label":"Nov 27, 20","volume":753487,"updated":1609377605000,"open":153.5},
{"date":"2020-11-25","symbol":"HCA","subkey":"","fClose":153.3689,"uOpen":153.94,"uClose":153.62,"high":155.46,"fOpen":153.6884,"low":152.5238,"changeOverTime":-0.10831205015091709,"fHigh":155.2059,"changePercent":0.0037,"id":"HISTORICAL_PRICES","marketChangeOverTime":-0.10831205015091709,"close":153.62,"key":"HCA","fLow":152.2745,"uHigh":155.46,"uVolume":1077101,"change":0.5699999999999932,"uLow":152.5238,"fVolume":1077101,"label":"Nov 25, 20","volume":1077101,"updated":1609377561000,"open":153.94},
{"date":"2020-11-24","symbol":"HCA","subkey":"","fClose":154.8065,"uOpen":150.99,"uClose":155.06,"high":155.64,"fOpen":150.7432,"low":149.55,"changeOverTime":-0.09995356396563733,"fHigh":155.3856,"changePercent":0.0094,"id":"HISTORICAL_PRICES","marketChangeOverTime":-0.09995356396563733,"close":155.06,"key":"HCA","fLow":149.3055,"uHigh":155.64,"uVolume":2493749,"change":1.4399999999999977,"uLow":149.55,"fVolume":2493749,"label":"Nov 24, 20","volume":2493749,"updated":1609377590000,"open":150.99},
{"date":"2020-11-23","symbol":"HCA","subkey":"","fClose":149.1558,"uOpen":148.89,"uClose":149.4,"high":151.31,"fOpen":148.6466,"low":148.24,"changeOverTime":-0.1328070582772231,"fHigh":151.0627,"changePercent":-0.0365,"id":"HISTORICAL_PRICES","marketChangeOverTime":-0.1328070582772231,"close":149.4,"key":"HCA","fLow":147.9977,"uHigh":151.31,"uVolume":1244172,"change":-5.659999999999997,"uLow":148.24,"fVolume":1244172,"label":"Nov 23, 20","volume":1244172,"updated":1609377483000,"open":148.89},
{"date":"2020-11-20","symbol":"HCA","subkey":"","fClose":147.0992,"uOpen":150.92,"uClose":147.34,"high":151.39,"fOpen":150.6733,"low":147.01,"changeOverTime":-0.14476433712560946,"fHigh":151.1425,"changePercent":-0.0138,"id":"HISTORICAL_PRICES","marketChangeOverTime":-0.14476433712560946,"close":147.34,"key":"HCA","fLow":146.7697,"uHigh":151.39,"uVolume":1337301,"change":-2.0600000000000023,"uLow":147.01,"fVolume":1337301,"label":"Nov 20, 20","volume":1337301,"updated":1609377631000,"open":150.92},
{"date":"2020-11-19","symbol":"HCA","subkey":"","fClose":150.6034,"uOpen":150.2,"uClose":150.85,"high":151.24,"fOpen":149.9545,"low":147.67,"changeOverTime":-0.12439052704899005,"fHigh":150.9928,"changePercent":0.0238,"id":"HISTORICAL_PRICES","marketChangeOverTime":-0.12439052704899005,"close":150.85,"key":"HCA","fLow":147.4286,"uHigh":151.24,"uVolume":2141812,"change":3.509999999999991,"uLow":147.67,"fVolume":2141812,"label":"Nov 19, 20","volume":2141812,"updated":1609377613000,"open":150.2},
{"date":"2020-11-18","symbol":"HCA","subkey":"","fClose":150.9928,"uOpen":152.11,"uClose":151.24,"high":154.475,"fOpen":151.8614,"low":150.1,"changeOverTime":-0.12212677037381003,"fHigh":154.2225,"changePercent":0.0026,"id":"HISTORICAL_PRICES","marketChangeOverTime":-0.12212677037381003,"close":151.24,"key":"HCA","fLow":149.8546,"uHigh":154.475,"uVolume":1219385,"change":0.3900000000000148,"uLow":150.1,"fVolume":1219385,"label":"Nov 18, 20","volume":1219385,"updated":1609377619000,"open":152.11},
{"date":"2020-11-17","symbol":"HCA","subkey":"","fClose":152.7799,"uOpen":150.32,"uClose":153.03,"high":155.84,"fOpen":150.0743,"low":149.14,"changeOverTime":-0.11173670768516368,"fHigh":155.5853,"changePercent":0.0118,"id":"HISTORICAL_PRICES","marketChangeOverTime":-0.11173670768516368,"close":153.03,"key":"HCA","fLow":148.8962,"uHigh":155.84,"uVolume":1587632,"change":1.789999999999992,"uLow":149.14,"fVolume":1587632,"label":"Nov 17, 20","volume":1587632,"updated":1609377590000,"open":150.32},
{"date":"2020-11-16","symbol":"HCA","subkey":"","fClose":151.5718,"uOpen":151.75,"uClose":151.82,"high":153.92,"fOpen":151.5019,"low":150.23,"changeOverTime":-0.11876015788251688,"fHigh":153.6684,"changePercent":-0.0079,"id":"HISTORICAL_PRICES","marketChangeOverTime":-0.11876015788251688,"close":151.82,"key":"HCA","fLow":149.9844,"uHigh":153.92,"uVolume":1803838,"change":-1.210000000000008,"uLow":150.23,"fVolume":1803838,"label":"Nov 16, 20","volume":1803838,"updated":1609377444000,"open":151.75},
{"date":"2020-11-13","symbol":"HCA","subkey":"","fClose":149.5052,"uOpen":145.01,"uClose":149.75,"high":149.97,"fOpen":144.773,"low":144.93,"changeOverTime":-0.1307754817738565,"fHigh":149.7249,"changePercent":-0.0136,"id":"HISTORICAL_PRICES","marketChangeOverTime":-0.1307754817738565,"close":149.75,"key":"HCA","fLow":144.6931,"uHigh":149.97,"uVolume":1373778,"change":-2.069999999999993,"uLow":144.93,"fVolume":1373778,"label":"Nov 13, 20","volume":1373778,"updated":1609377561000,"open":145.01},
{"date":"2020-11-12","symbol":"HCA","subkey":"","fClose":144.3537,"uOpen":144.61,"uClose":144.59,"high":147.83,"fOpen":144.3736,"low":142.4702,"changeOverTime":-0.1607267239377757,"fHigh":147.5884,"changePercent":-0.0345,"id":"HISTORICAL_PRICES","marketChangeOverTime":-0.1607267239377757,"close":144.59,"key":"HCA","fLow":142.2373,"uHigh":147.83,"uVolume":2101849,"change":-5.159999999999997,"uLow":142.4702,"fVolume":2101849,"label":"Nov 12, 20","volume":2101849,"updated":1609377631000,"open":144.61},
{"date":"2020-11-11","symbol":"HCA","subkey":"","fClose":145.2322,"uOpen":151.63,"uClose":145.47,"high":152,"fOpen":151.3821,"low":144.78,"changeOverTime":-0.15561876015788254,"fHigh":151.7515,"changePercent":0.0061,"id":"HISTORICAL_PRICES","marketChangeOverTime":-0.15561876015788254,"close":145.47,"key":"HCA","fLow":144.5433,"uHigh":152,"uVolume":1456302,"change":0.8799999999999955,"uLow":144.78,"fVolume":1456302,"label":"Nov 11, 20","volume":1456302,"updated":1609377590000,"open":151.63},
{"date":"2020-11-10","symbol":"HCA","subkey":"","fClose":151.8614,"uOpen":146.38,"uClose":152.11,"high":154.94,"fOpen":146.1407,"low":146.38,"changeOverTime":-0.11707685163687014,"fHigh":154.6867,"changePercent":0.0456,"id":"HISTORICAL_PRICES","marketChangeOverTime":-0.11707685163687014,"close":152.11,"key":"HCA","fLow":146.1407,"uHigh":154.94,"uVolume":2497460,"change":6.640000000000015,"uLow":146.38,"fVolume":2497460,"label":"Nov 10, 20","volume":2497460,"updated":1609377644000,"open":146.38},
{"date":"2020-11-09","symbol":"HCA","subkey":"","fClose":147.0792,"uOpen":147.69,"uClose":147.32,"high":152.67,"fOpen":147.4486,"low":145.99,"changeOverTime":-0.14488042721151617,"fHigh":152.4204,"changePercent":-0.0315,"id":"HISTORICAL_PRICES","marketChangeOverTime":-0.14488042721151617,"close":147.32,"key":"HCA","fLow":145.7514,"uHigh":152.67,"uVolume":3778714,"change":-4.7900000000000205,"uLow":145.99,"fVolume":3778714,"label":"Nov 9, 20","volume":3778714,"updated":1609377519000,"open":147.69},
{"date":"2020-11-06","symbol":"HCA","subkey":"","fClose":138.2736,"uOpen":137.33,"uClose":138.5,"high":139.56,"fOpen":137.1055,"low":136.35,"changeOverTime":-0.1960761550963548,"fHigh":139.3319,"changePercent":-0.0599,"id":"HISTORICAL_PRICES","marketChangeOverTime":-0.1960761550963548,"close":138.5,"key":"HCA","fLow":136.1271,"uHigh":139.56,"uVolume":1004251,"change":-8.819999999999993,"uLow":136.35,"fVolume":1004251,"label":"Nov 6, 20","volume":1004251,"updated":1609377631000,"open":137.33},
{"date":"2020-11-05","symbol":"HCA","subkey":"","fClose":137.3351,"uOpen":133.93,"uClose":137.56,"high":140.4899,"fOpen":133.7111,"low":133.52,"changeOverTime":-0.20153238913396795,"fHigh":140.2603,"changePercent":-0.0068,"id":"HISTORICAL_PRICES","marketChangeOverTime":-0.20153238913396795,"close":137.56,"key":"HCA","fLow":133.3017,"uHigh":140.4899,"uVolume":1681813,"change":-0.9399999999999977,"uLow":133.52,"fVolume":1681813,"label":"Nov 5, 20","volume":1681813,"updated":1609377431000,"open":133.93},
{"date":"2020-11-04","symbol":"HCA","subkey":"","fClose":131.5846,"uOpen":135.99,"uClose":131.8,"high":138.63,"fOpen":135.7677,"low":131.56,"changeOverTime":-0.234966333875087,"fHigh":138.4034,"changePercent":-0.0419,"id":"HISTORICAL_PRICES","marketChangeOverTime":-0.234966333875087,"close":131.8,"key":"HCA","fLow":131.3449,"uHigh":138.63,"uVolume":2301337,"change":-5.759999999999991,"uLow":131.56,"fVolume":2301337,"label":"Nov 4, 20","volume":2301337,"updated":1609377644000,"open":135.99},
{"date":"2020-11-03","symbol":"HCA","subkey":"","fClose":135.8675,"uOpen":132.79,"uClose":136.09,"high":137.22,"fOpen":132.5729,"low":132.35,"changeOverTime":-0.21006501044810771,"fHigh":136.9957,"changePercent":0.0325,"id":"HISTORICAL_PRICES","marketChangeOverTime":-0.21006501044810771,"close":136.09,"key":"HCA","fLow":132.1337,"uHigh":137.22,"uVolume":1656241,"change":4.289999999999992,"uLow":132.35,"fVolume":1656241,"label":"Nov 3, 20","volume":1656241,"updated":1609377613000,"open":132.79},
{"date":"2020-11-02","symbol":"HCA","subkey":"","fClose":130.3865,"uOpen":126.11,"uClose":130.6,"high":130.74,"fOpen":125.9039,"low":125.18,"changeOverTime":-0.24193173902948692,"fHigh":130.5263,"changePercent":-0.0403,"id":"HISTORICAL_PRICES","marketChangeOverTime":-0.24193173902948692,"close":130.6,"key":"HCA","fLow":124.9754,"uHigh":130.74,"uVolume":2012959,"change":-5.490000000000009,"uLow":125.18,"fVolume":2012959,"label":"Nov 2, 20","volume":2012959,"updated":1609377634000,"open":126.11},
{"date":"2020-10-30","symbol":"HCA","subkey":"","fClose":123.7374,"uOpen":125,"uClose":123.94,"high":126.68,"fOpen":124.7957,"low":121.91,"changeOverTime":-0.2805897376364059,"fHigh":126.4729,"changePercent":-0.051,"id":"HISTORICAL_PRICES","marketChangeOverTime":-0.2805897376364059,"close":123.94,"key":"HCA","fLow":121.7107,"uHigh":126.68,"uVolume":1718848,"change":-6.659999999999997,"uLow":121.91,"fVolume":1718848,"label":"Oct 30, 20","volume":1718848,"updated":1609377634000,"open":125},
{"date":"2020-10-29","symbol":"HCA","subkey":"","fClose":125.195,"uOpen":126.17,"uClose":125.4,"high":127.27,"fOpen":125.9638,"low":123.82,"changeOverTime":-0.2721151613652194,"fHigh":127.062,"changePercent":0.0118,"id":"HISTORICAL_PRICES","marketChangeOverTime":-0.2721151613652194,"close":125.4,"key":"HCA","fLow":123.6176,"uHigh":127.27,"uVolume":1343898,"change":1.460000000000008,"uLow":123.82,"fVolume":1343898,"label":"Oct 29, 20","volume":1343898,"updated":1609377613000,"open":126.17},
{"date":"2020-10-28","symbol":"HCA","subkey":"","fClose":126.3431,"uOpen":128.04,"uClose":126.55,"high":130.08,"fOpen":127.8307,"low":125.5507,"changeOverTime":-0.2654399814255863,"fHigh":129.8674,"changePercent":0.0092,"id":"HISTORICAL_PRICES","marketChangeOverTime":-0.2654399814255863,"close":126.55,"key":"HCA","fLow":125.3455,"uHigh":130.08,"uVolume":1342604,"change":1.1499999999999915,"uLow":125.5507,"fVolume":1342604,"label":"Oct 28, 20","volume":1342604,"updated":1609377561000,"open":128.04},
{"date":"2020-10-27","symbol":"HCA","subkey":"","fClose":130.3466,"uOpen":134.71,"uClose":130.56,"high":135.4,"fOpen":134.4898,"low":130.4,"changeOverTime":-0.2421639192013002,"fHigh":135.1787,"changePercent":0.0317,"id":"HISTORICAL_PRICES","marketChangeOverTime":-0.2421639192013002,"close":130.56,"key":"HCA","fLow":130.1868,"uHigh":135.4,"uVolume":1450959,"change":4.010000000000005,"uLow":130.4,"fVolume":1450959,"label":"Oct 27, 20","volume":1450959,"updated":1609377586000,"open":134.71},
{"date":"2020-10-26","symbol":"HCA","subkey":"","fClose":135.2086,"uOpen":134.5,"uClose":135.43,"high":137.45,"fOpen":134.2801,"low":130.49,"changeOverTime":-0.21389598328302759,"fHigh":137.2253,"changePercent":0.0373,"id":"HISTORICAL_PRICES","marketChangeOverTime":-0.21389598328302759,"close":135.43,"key":"HCA","fLow":130.2767,"uHigh":137.45,"uVolume":1966779,"change":4.8700000000000045,"uLow":130.49,"fVolume":1966779,"label":"Oct 26, 20","volume":1966779,"updated":1609377444000,"open":134.5},
{"date":"2020-10-23","symbol":"HCA","subkey":"","fClose":136.3667,"uOpen":136.81,"uClose":136.59,"high":137.84,"fOpen":136.5864,"low":134.8,"changeOverTime":-0.20716275830044112,"fHigh":137.6147,"changePercent":0.0086,"id":"HISTORICAL_PRICES","marketChangeOverTime":-0.20716275830044112,"close":136.59,"key":"HCA","fLow":134.5797,"uHigh":137.84,"uVolume":897246,"change":1.1599999999999966,"uLow":134.8,"fVolume":897246,"label":"Oct 23, 20","volume":897246,"updated":1609377586000,"open":136.81},
{"date":"2020-10-22","symbol":"HCA","subkey":"","fClose":134.989,"uOpen":135.78,"uClose":135.21,"high":138.11,"fOpen":135.5581,"low":134.43,"changeOverTime":-0.21517297422800089,"fHigh":137.8842,"changePercent":-0.0101,"id":"HISTORICAL_PRICES","marketChangeOverTime":-0.21517297422800089,"close":135.21,"key":"HCA","fLow":134.2103,"uHigh":138.11,"uVolume":1485770,"change":-1.3799999999999955,"uLow":134.43,"fVolume":1485770,"label":"Oct 22, 20","volume":1485770,"updated":1609377605000,"open":135.78},
{"date":"2020-10-21","symbol":"HCA","subkey":"","fClose":135.7577,"uOpen":135.59,"uClose":135.98,"high":138.89,"fOpen":135.3684,"low":135.59,"changeOverTime":-0.21070350592059445,"fHigh":138.663,"changePercent":0.0057,"id":"HISTORICAL_PRICES","marketChangeOverTime":-0.21070350592059445,"close":135.98,"key":"HCA","fLow":135.3684,"uHigh":138.89,"uVolume":1257266,"change":0.7699999999999818,"uLow":135.59,"fVolume":1257266,"label":"Oct 21, 20","volume":1257266,"updated":1609377648000,"open":135.59},
{"date":"2020-10-20","symbol":"HCA","subkey":"","fClose":136.197,"uOpen":134.33,"uClose":136.42,"high":137.98,"fOpen":134.1104,"low":133.71,"changeOverTime":-0.20814952403064785,"fHigh":137.7545,"changePercent":0.0032,"id":"HISTORICAL_PRICES","marketChangeOverTime":-0.20814952403064785,"close":136.42,"key":"HCA","fLow":133.4914,"uHigh":137.98,"uVolume":981900,"change":0.4399999999999977,"uLow":133.71,"fVolume":981900,"label":"Oct 20, 20","volume":981900,"updated":1609377634000,"open":134.33},
{"date":"2020-10-19","symbol":"HCA","subkey":"","fClose":134.1104,"uOpen":134.56,"uClose":134.33,"high":136.79,"fOpen":134.34,"low":133.4,"changeOverTime":-0.22028093800789406,"fHigh":136.5664,"changePercent":-0.0153,"id":"HISTORICAL_PRICES","marketChangeOverTime":-0.22028093800789406,"close":134.33,"key":"HCA","fLow":133.1819,"uHigh":136.79,"uVolume":894613,"change":-2.089999999999975,"uLow":133.4,"fVolume":894613,"label":"Oct 19, 20","volume":894613,"updated":1609377619000,"open":134.56},
{"date":"2020-10-16","symbol":"HCA","subkey":"","fClose":134.8991,"uOpen":137.79,"uClose":135.12,"high":139.48,"fOpen":137.5648,"low":134.72,"changeOverTime":-0.2156953796145809,"fHigh":139.252,"changePercent":0.0059,"id":"HISTORICAL_PRICES","marketChangeOverTime":-0.2156953796145809,"close":135.12,"key":"HCA","fLow":134.4998,"uHigh":139.48,"uVolume":1197578,"change":0.789999999999992,"uLow":134.72,"fVolume":1197578,"label":"Oct 16, 20","volume":1197578,"updated":1609377652000,"open":137.79},
{"date":"2020-10-15","symbol":"HCA","subkey":"","fClose":137.5648,"uOpen":132.5,"uClose":137.79,"high":138.51,"fOpen":132.2834,"low":132.0436,"changeOverTime":-0.20019735314604137,"fHigh":138.2836,"changePercent":0.0198,"id":"HISTORICAL_PRICES","marketChangeOverTime":-0.20019735314604137,"close":137.79,"key":"HCA","fLow":131.8278,"uHigh":138.51,"uVolume":1327778,"change":2.6699999999999875,"uLow":132.0436,"fVolume":1327778,"label":"Oct 15, 20","volume":1327778,"updated":1609377634000,"open":132.5},
{"date":"2020-10-14","symbol":"HCA","subkey":"","fClose":134.4399,"uOpen":132.62,"uClose":134.66,"high":136.76,"fOpen":132.4032,"low":132.25,"changeOverTime":-0.2183654515904342,"fHigh":136.5364,"changePercent":-0.0227,"id":"HISTORICAL_PRICES","marketChangeOverTime":-0.2183654515904342,"close":134.66,"key":"HCA","fLow":132.0338,"uHigh":136.76,"uVolume":1197140,"change":-3.1299999999999955,"uLow":132.25,"fVolume":1197140,"label":"Oct 14, 20","volume":1197140,"updated":1609377634000,"open":132.62},
{"date":"2020-10-13","symbol":"HCA","subkey":"","fClose":132.7227,"uOpen":130.28,"uClose":132.94,"high":133.69,"fOpen":130.067,"low":128.32,"changeOverTime":-0.22834919897840728,"fHigh":133.4715,"changePercent":-0.0128,"id":"HISTORICAL_PRICES","marketChangeOverTime":-0.22834919897840728,"close":132.94,"key":"HCA","fLow":128.1102,"uHigh":133.69,"uVolume":1435710,"change":-1.7199999999999989,"uLow":128.32,"fVolume":1435710,"label":"Oct 13, 20","volume":1435710,"updated":1609377652000,"open":130.28},
{"date":"2020-10-12","symbol":"HCA","subkey":"","fClose":130.0171,"uOpen":135,"uClose":130.23,"high":135.285,"fOpen":134.7793,"low":129.89,"changeOverTime":-0.2440794056187602,"fHigh":135.0639,"changePercent":-0.0204,"id":"HISTORICAL_PRICES","marketChangeOverTime":-0.2440794056187602,"close":130.23,"key":"HCA","fLow":129.6777,"uHigh":135.285,"uVolume":1332648,"change":-2.710000000000008,"uLow":129.89,"fVolume":1332648,"label":"Oct 12, 20","volume":1332648,"updated":1609377483000,"open":135},
{"date":"2020-10-09","symbol":"HCA","subkey":"","fClose":133.741,"uOpen":139.5,"uClose":133.96,"high":140,"fOpen":139.272,"low":133.2,"changeOverTime":-0.22242860459716737,"fHigh":139.7712,"changePercent":0.0286,"id":"HISTORICAL_PRICES","marketChangeOverTime":-0.22242860459716737,"close":133.96,"key":"HCA","fLow":132.9823,"uHigh":140,"uVolume":2754267,"change":3.730000000000018,"uLow":133.2,"fVolume":2754267,"label":"Oct 9, 20","volume":2754267,"updated":1609377431000,"open":139.5}]