[{"date":"2021-01-08","symbol":"TME","subkey":"","fClose":21.05,"uOpen":20.6,"uClose":21.05,"high":21.08,"fOpen":20.6,"low":20.44,"changeOverTime":0,"fHigh":21.08,"changePercent":0,"id":"HISTORICAL_PRICES","marketChangeOverTime":0,"close":21.05,"key":"TME","fLow":20.44,"uHigh":21.08,"uVolume":12782196,"change":0,"uLow":20.44,"fVolume":12782196,"label":"Jan 8, 21","volume":12782196,"updated":1610158586000,"open":20.6},
{"date":"2021-01-07","symbol":"TME","subkey":"","fClose":20.6,"uOpen":20.18,"uClose":20.6,"high":20.71,"fOpen":20.18,"low":19.96,"changeOverTime":-0.021377672209026095,"fHigh":20.71,"changePercent":-0.0214,"id":"HISTORICAL_PRICES","marketChangeOverTime":-0.021377672209026095,"close":20.6,"key":"TME","fLow":19.96,"uHigh":20.71,"uVolume":13180665,"change":-0.4499999999999993,"uLow":19.96,"fVolume":13180665,"label":"Jan 7, 21","volume":13180665,"updated":1610072191000,"open":20.18},
{"date":"2021-01-06","symbol":"TME","subkey":"","fClose":20.95,"uOpen":20.1,"uClose":20.95,"high":21.2895,"fOpen":20.1,"low":20.1,"changeOverTime":-0.0047505938242280955,"fHigh":21.2895,"changePercent":0.017,"id":"HISTORICAL_PRICES","marketChangeOverTime":-0.0047505938242280955,"close":20.95,"key":"TME","fLow":20.1,"uHigh":21.2895,"uVolume":9285096,"change":0.34999999999999787,"uLow":20.1,"fVolume":9285096,"label":"Jan 6, 21","volume":9285096,"updated":1609984832000,"open":20.1},
{"date":"2021-01-05","symbol":"TME","subkey":"","fClose":20.46,"uOpen":19.57,"uClose":20.46,"high":20.48,"fOpen":19.57,"low":19.42,"changeOverTime":-0.02802850356294536,"fHigh":20.48,"changePercent":-0.0234,"id":"HISTORICAL_PRICES","marketChangeOverTime":-0.02802850356294536,"close":20.46,"key":"TME","fLow":19.42,"uHigh":20.48,"uVolume":9158379,"change":-0.48999999999999844,"uLow":19.42,"fVolume":9158379,"label":"Jan 5, 21","volume":9158379,"updated":1609897701000,"open":19.57},
{"date":"2021-01-04","symbol":"TME","subkey":"","fClose":19.37,"uOpen":19.3,"uClose":19.37,"high":19.54,"fOpen":19.3,"low":18.9,"changeOverTime":-0.07980997624703086,"fHigh":19.54,"changePercent":-0.0533,"id":"HISTORICAL_PRICES","marketChangeOverTime":-0.07980997624703086,"close":19.37,"key":"TME","fLow":18.9,"uHigh":19.54,"uVolume":8447281,"change":-1.0899999999999999,"uLow":18.9,"fVolume":8447281,"label":"Jan 4, 21","volume":8447281,"updated":1609812028000,"open":19.3},
{"date":"2020-12-31","symbol":"TME","subkey":"","fClose":19.24,"uOpen":19.2,"uClose":19.24,"high":19.29,"fOpen":19.2,"low":18.73,"changeOverTime":-0.08598574821852742,"fHigh":19.29,"changePercent":-0.0067,"id":"HISTORICAL_PRICES","marketChangeOverTime":-0.08598574821852742,"close":19.24,"key":"TME","fLow":18.73,"uHigh":19.29,"uVolume":6778632,"change":-0.13000000000000256,"uLow":18.73,"fVolume":6778632,"label":"Dec 31, 20","volume":6778632,"updated":1609468344000,"open":19.2},
{"date":"2020-12-30","symbol":"TME","subkey":"","fClose":19.22,"uOpen":19.2,"uClose":19.22,"high":20.18,"fOpen":19.2,"low":19.19,"changeOverTime":-0.08693586698337301,"fHigh":20.18,"changePercent":-0.001,"id":"HISTORICAL_PRICES","marketChangeOverTime":-0.08693586698337301,"close":19.22,"key":"TME","fLow":19.19,"uHigh":20.18,"uVolume":8695551,"change":-0.019999999999999574,"uLow":19.19,"fVolume":8695551,"label":"Dec 30, 20","volume":8695551,"updated":1609379306000,"open":19.2},
{"date":"2020-12-29","symbol":"TME","subkey":"","fClose":18.93,"uOpen":18.63,"uClose":18.93,"high":19.04,"fOpen":18.63,"low":18.42,"changeOverTime":-0.10071258907363424,"fHigh":19.04,"changePercent":-0.0151,"id":"HISTORICAL_PRICES","marketChangeOverTime":-0.10071258907363424,"close":18.93,"key":"TME","fLow":18.42,"uHigh":19.04,"uVolume":7352831,"change":-0.28999999999999915,"uLow":18.42,"fVolume":7352831,"label":"Dec 29, 20","volume":7352831,"updated":1609292904000,"open":18.63},
{"date":"2020-12-28","symbol":"TME","subkey":"","fClose":18.54,"uOpen":18.87,"uClose":18.54,"high":19.03,"fOpen":18.87,"low":18.03,"changeOverTime":-0.11923990498812359,"fHigh":19.03,"changePercent":-0.0206,"id":"HISTORICAL_PRICES","marketChangeOverTime":-0.11923990498812359,"close":18.54,"key":"TME","fLow":18.03,"uHigh":19.03,"uVolume":9558386,"change":-0.39000000000000057,"uLow":18.03,"fVolume":9558386,"label":"Dec 28, 20","volume":9558386,"updated":1609206503000,"open":18.87},
{"date":"2020-12-24","symbol":"TME","subkey":"","fClose":18.91,"uOpen":18.48,"uClose":18.91,"high":18.93,"fOpen":18.48,"low":18.41,"changeOverTime":-0.10166270783847983,"fHigh":18.93,"changePercent":0.02,"id":"HISTORICAL_PRICES","marketChangeOverTime":-0.10166270783847983,"close":18.91,"key":"TME","fLow":18.41,"uHigh":18.93,"uVolume":4993093,"change":0.370000000000001,"uLow":18.41,"fVolume":4993093,"label":"Dec 24, 20","volume":4993093,"updated":1608860909000,"open":18.48},
{"date":"2020-12-23","symbol":"TME","subkey":"","fClose":18.83,"uOpen":18.95,"uClose":18.83,"high":19.15,"fOpen":18.95,"low":18.81,"changeOverTime":-0.10546318289786234,"fHigh":19.15,"changePercent":-0.0042,"id":"HISTORICAL_PRICES","marketChangeOverTime":-0.10546318289786234,"close":18.83,"key":"TME","fLow":18.81,"uHigh":19.15,"uVolume":2480322,"change":-0.08000000000000185,"uLow":18.81,"fVolume":2480322,"label":"Dec 23, 20","volume":2480322,"updated":1608775227000,"open":18.95},
{"date":"2020-12-22","symbol":"TME","subkey":"","fClose":18.88,"uOpen":19,"uClose":18.88,"high":19,"fOpen":19,"low":18.62,"changeOverTime":-0.10308788598574829,"fHigh":19,"changePercent":0.0027,"id":"HISTORICAL_PRICES","marketChangeOverTime":-0.10308788598574829,"close":18.88,"key":"TME","fLow":18.62,"uHigh":19,"uVolume":4817637,"change":0.05000000000000071,"uLow":18.62,"fVolume":4817637,"label":"Dec 22, 20","volume":4817637,"updated":1608688827000,"open":19},
{"date":"2020-12-21","symbol":"TME","subkey":"","fClose":18.8,"uOpen":18.41,"uClose":18.8,"high":19.03,"fOpen":18.41,"low":18.31,"changeOverTime":-0.10688836104513064,"fHigh":19.03,"changePercent":-0.0042,"id":"HISTORICAL_PRICES","marketChangeOverTime":-0.10688836104513064,"close":18.8,"key":"TME","fLow":18.31,"uHigh":19.03,"uVolume":10129418,"change":-0.0799999999999983,"uLow":18.31,"fVolume":10129418,"label":"Dec 21, 20","volume":10129418,"updated":1608603392000,"open":18.41},
{"date":"2020-12-18","symbol":"TME","subkey":"","fClose":18.66,"uOpen":18.54,"uClose":18.66,"high":18.68,"fOpen":18.54,"low":18.16,"changeOverTime":-0.1135391923990499,"fHigh":18.68,"changePercent":-0.0074,"id":"HISTORICAL_PRICES","marketChangeOverTime":-0.1135391923990499,"close":18.66,"key":"TME","fLow":18.16,"uHigh":18.68,"uVolume":8953781,"change":-0.14000000000000057,"uLow":18.16,"fVolume":8953781,"label":"Dec 18, 20","volume":8953781,"updated":1608344193000,"open":18.54},
{"date":"2020-12-17","symbol":"TME","subkey":"","fClose":18.45,"uOpen":17.9,"uClose":18.45,"high":18.52,"fOpen":17.9,"low":17.87,"changeOverTime":-0.1235154394299288,"fHigh":18.52,"changePercent":-0.0113,"id":"HISTORICAL_PRICES","marketChangeOverTime":-0.1235154394299288,"close":18.45,"key":"TME","fLow":17.87,"uHigh":18.52,"uVolume":8434226,"change":-0.21000000000000085,"uLow":17.87,"fVolume":8434226,"label":"Dec 17, 20","volume":8434226,"updated":1608256823000,"open":17.9},
{"date":"2020-12-16","symbol":"TME","subkey":"","fClose":17.85,"uOpen":18.58,"uClose":17.85,"high":18.7,"fOpen":18.58,"low":17.52,"changeOverTime":-0.15201900237529686,"fHigh":18.7,"changePercent":-0.0325,"id":"HISTORICAL_PRICES","marketChangeOverTime":-0.15201900237529686,"close":17.85,"key":"TME","fLow":17.52,"uHigh":18.7,"uVolume":18499130,"change":-0.5999999999999979,"uLow":17.52,"fVolume":18499130,"label":"Dec 16, 20","volume":18499130,"updated":1608169706000,"open":18.58},
{"date":"2020-12-15","symbol":"TME","subkey":"","fClose":19.05,"uOpen":18.96,"uClose":19.05,"high":19.14,"fOpen":18.96,"low":18.46,"changeOverTime":-0.09501187648456057,"fHigh":19.14,"changePercent":0.0672,"id":"HISTORICAL_PRICES","marketChangeOverTime":-0.09501187648456057,"close":19.05,"key":"TME","fLow":18.46,"uHigh":19.14,"uVolume":5717112,"change":1.1999999999999993,"uLow":18.46,"fVolume":5717112,"label":"Dec 15, 20","volume":5717112,"updated":1608085943000,"open":18.96},
{"date":"2020-12-14","symbol":"TME","subkey":"","fClose":18.88,"uOpen":18.89,"uClose":18.88,"high":19.32,"fOpen":18.89,"low":18.59,"changeOverTime":-0.10308788598574829,"fHigh":19.32,"changePercent":-0.0089,"id":"HISTORICAL_PRICES","marketChangeOverTime":-0.10308788598574829,"close":18.88,"key":"TME","fLow":18.59,"uHigh":19.32,"uVolume":5856193,"change":-0.1700000000000017,"uLow":18.59,"fVolume":5856193,"label":"Dec 14, 20","volume":5856193,"updated":1608004822000,"open":18.89},
{"date":"2020-12-11","symbol":"TME","subkey":"","fClose":18.72,"uOpen":18.6,"uClose":18.72,"high":19.555,"fOpen":18.6,"low":18.515,"changeOverTime":-0.11068883610451315,"fHigh":19.555,"changePercent":-0.0085,"id":"HISTORICAL_PRICES","marketChangeOverTime":-0.11068883610451315,"close":18.72,"key":"TME","fLow":18.515,"uHigh":19.555,"uVolume":12692564,"change":-0.16000000000000014,"uLow":18.515,"fVolume":12692564,"label":"Dec 11, 20","volume":12692564,"updated":1607739386000,"open":18.6},
{"date":"2020-12-10","symbol":"TME","subkey":"","fClose":18.61,"uOpen":18.55,"uClose":18.61,"high":18.68,"fOpen":18.55,"low":18.085,"changeOverTime":-0.11591448931116395,"fHigh":18.68,"changePercent":-0.0059,"id":"HISTORICAL_PRICES","marketChangeOverTime":-0.11591448931116395,"close":18.61,"key":"TME","fLow":18.085,"uHigh":18.68,"uVolume":9507800,"change":-0.10999999999999943,"uLow":18.085,"fVolume":9507800,"label":"Dec 10, 20","volume":9507800,"updated":1607653076000,"open":18.55},
{"date":"2020-12-09","symbol":"TME","subkey":"","fClose":18.88,"uOpen":18,"uClose":18.88,"high":19.63,"fOpen":18,"low":17.94,"changeOverTime":-0.10308788598574829,"fHigh":19.63,"changePercent":0.0145,"id":"HISTORICAL_PRICES","marketChangeOverTime":-0.10308788598574829,"close":18.88,"key":"TME","fLow":17.94,"uHigh":19.63,"uVolume":22107154,"change":0.2699999999999996,"uLow":17.94,"fVolume":22107154,"label":"Dec 9, 20","volume":22107154,"updated":1607572100000,"open":18},
{"date":"2020-12-08","symbol":"TME","subkey":"","fClose":18,"uOpen":16.76,"uClose":18,"high":18.06,"fOpen":16.76,"low":16.65,"changeOverTime":-0.1448931116389549,"fHigh":18.06,"changePercent":-0.0466,"id":"HISTORICAL_PRICES","marketChangeOverTime":-0.1448931116389549,"close":18,"key":"TME","fLow":16.65,"uHigh":18.06,"uVolume":15322978,"change":-0.879999999999999,"uLow":16.65,"fVolume":15322978,"label":"Dec 8, 20","volume":15322978,"updated":1607489303000,"open":16.76},
{"date":"2020-12-07","symbol":"TME","subkey":"","fClose":16.81,"uOpen":16.74,"uClose":16.81,"high":16.88,"fOpen":16.74,"low":16.39,"changeOverTime":-0.20142517814726849,"fHigh":16.88,"changePercent":-0.0661,"id":"HISTORICAL_PRICES","marketChangeOverTime":-0.20142517814726849,"close":16.81,"key":"TME","fLow":16.39,"uHigh":16.88,"uVolume":7185855,"change":-1.1900000000000013,"uLow":16.39,"fVolume":7185855,"label":"Dec 7, 20","volume":7185855,"updated":1607394472000,"open":16.74},
{"date":"2020-12-04","symbol":"TME","subkey":"","fClose":16.73,"uOpen":16.72,"uClose":16.73,"high":16.9,"fOpen":16.72,"low":16.645,"changeOverTime":-0.20522565320665084,"fHigh":16.9,"changePercent":-0.0048,"id":"HISTORICAL_PRICES","marketChangeOverTime":-0.20522565320665084,"close":16.73,"key":"TME","fLow":16.645,"uHigh":16.9,"uVolume":5154438,"change":-0.0799999999999983,"uLow":16.645,"fVolume":5154438,"label":"Dec 4, 20","volume":5154438,"updated":1607134589000,"open":16.72},
{"date":"2020-12-03","symbol":"TME","subkey":"","fClose":16.74,"uOpen":16.56,"uClose":16.74,"high":16.89,"fOpen":16.56,"low":16.46,"changeOverTime":-0.20475059382422814,"fHigh":16.89,"changePercent":0.0006,"id":"HISTORICAL_PRICES","marketChangeOverTime":-0.20475059382422814,"close":16.74,"key":"TME","fLow":16.46,"uHigh":16.89,"uVolume":5318945,"change":0.00999999999999801,"uLow":16.46,"fVolume":5318945,"label":"Dec 3, 20","volume":5318945,"updated":1607046487000,"open":16.56},
{"date":"2020-12-02","symbol":"TME","subkey":"","fClose":16.44,"uOpen":16.35,"uClose":16.44,"high":16.55,"fOpen":16.35,"low":16.07,"changeOverTime":-0.21900237529691208,"fHigh":16.55,"changePercent":-0.0179,"id":"HISTORICAL_PRICES","marketChangeOverTime":-0.21900237529691208,"close":16.44,"key":"TME","fLow":16.07,"uHigh":16.55,"uVolume":10607661,"change":-0.29999999999999716,"uLow":16.07,"fVolume":10607661,"label":"Dec 2, 20","volume":10607661,"updated":1607001055000,"open":16.35},
{"date":"2020-12-01","symbol":"TME","subkey":"","fClose":16.41,"uOpen":16.73,"uClose":16.41,"high":16.81,"fOpen":16.73,"low":16.295,"changeOverTime":-0.22042755344418055,"fHigh":16.81,"changePercent":-0.0018,"id":"HISTORICAL_PRICES","marketChangeOverTime":-0.22042755344418055,"close":16.41,"key":"TME","fLow":16.295,"uHigh":16.81,"uVolume":15142163,"change":-0.030000000000001137,"uLow":16.295,"fVolume":15142163,"label":"Dec 1, 20","volume":15142163,"updated":1606882673000,"open":16.73},
{"date":"2020-11-30","symbol":"TME","subkey":"","fClose":16.76,"uOpen":16.97,"uClose":16.76,"high":16.99,"fOpen":16.97,"low":16.305,"changeOverTime":-0.20380047505938237,"fHigh":16.99,"changePercent":0.0213,"id":"HISTORICAL_PRICES","marketChangeOverTime":-0.20380047505938237,"close":16.76,"key":"TME","fLow":16.305,"uHigh":16.99,"uVolume":15673623,"change":0.3500000000000014,"uLow":16.305,"fVolume":15673623,"label":"Nov 30, 20","volume":15673623,"updated":1606833116000,"open":16.97},
{"date":"2020-11-27","symbol":"TME","subkey":"","fClose":17,"uOpen":16.59,"uClose":17,"high":17.13,"fOpen":16.59,"low":16.51,"changeOverTime":-0.19239904988123518,"fHigh":17.13,"changePercent":0.0143,"id":"HISTORICAL_PRICES","marketChangeOverTime":-0.19239904988123518,"close":17,"key":"TME","fLow":16.51,"uHigh":17.13,"uVolume":6035112,"change":0.23999999999999844,"uLow":16.51,"fVolume":6035112,"label":"Nov 27, 20","volume":6035112,"updated":1606830572000,"open":16.59},
{"date":"2020-11-25","symbol":"TME","subkey":"","fClose":16.71,"uOpen":16.46,"uClose":16.71,"high":16.72,"fOpen":16.46,"low":16.125,"changeOverTime":-0.20617577197149642,"fHigh":16.72,"changePercent":-0.0171,"id":"HISTORICAL_PRICES","marketChangeOverTime":-0.20617577197149642,"close":16.71,"key":"TME","fLow":16.125,"uHigh":16.72,"uVolume":6365205,"change":-0.28999999999999915,"uLow":16.125,"fVolume":6365205,"label":"Nov 25, 20","volume":6365205,"updated":1606830572000,"open":16.46},
{"date":"2020-11-24","symbol":"TME","subkey":"","fClose":16.48,"uOpen":16.41,"uClose":16.48,"high":16.505,"fOpen":16.41,"low":16.27,"changeOverTime":-0.2171021377672209,"fHigh":16.505,"changePercent":-0.0138,"id":"HISTORICAL_PRICES","marketChangeOverTime":-0.2171021377672209,"close":16.48,"key":"TME","fLow":16.27,"uHigh":16.505,"uVolume":11542542,"change":-0.23000000000000043,"uLow":16.27,"fVolume":11542542,"label":"Nov 24, 20","volume":11542542,"updated":1606830572000,"open":16.41},
{"date":"2020-11-23","symbol":"TME","subkey":"","fClose":16.5,"uOpen":16.76,"uClose":16.5,"high":16.76,"fOpen":16.76,"low":16.2,"changeOverTime":-0.21615201900237532,"fHigh":16.76,"changePercent":0.0012,"id":"HISTORICAL_PRICES","marketChangeOverTime":-0.21615201900237532,"close":16.5,"key":"TME","fLow":16.2,"uHigh":16.76,"uVolume":18519907,"change":0.019999999999999574,"uLow":16.2,"fVolume":18519907,"label":"Nov 23, 20","volume":18519907,"updated":1606830572000,"open":16.76},
{"date":"2020-11-20","symbol":"TME","subkey":"","fClose":16.73,"uOpen":16.43,"uClose":16.73,"high":16.8,"fOpen":16.43,"low":16.24,"changeOverTime":-0.20522565320665084,"fHigh":16.8,"changePercent":0.0139,"id":"HISTORICAL_PRICES","marketChangeOverTime":-0.20522565320665084,"close":16.73,"key":"TME","fLow":16.24,"uHigh":16.8,"uVolume":12063781,"change":0.23000000000000043,"uLow":16.24,"fVolume":12063781,"label":"Nov 20, 20","volume":12063781,"updated":1606830572000,"open":16.43},
{"date":"2020-11-19","symbol":"TME","subkey":"","fClose":16.4,"uOpen":16,"uClose":16.4,"high":16.47,"fOpen":16,"low":15.72,"changeOverTime":-0.22090261282660342,"fHigh":16.47,"changePercent":-0.0197,"id":"HISTORICAL_PRICES","marketChangeOverTime":-0.22090261282660342,"close":16.4,"key":"TME","fLow":15.72,"uHigh":16.47,"uVolume":7648119,"change":-0.33000000000000185,"uLow":15.72,"fVolume":7648119,"label":"Nov 19, 20","volume":7648119,"updated":1606830572000,"open":16},
{"date":"2020-11-18","symbol":"TME","subkey":"","fClose":16.12,"uOpen":16.19,"uClose":16.12,"high":16.19,"fOpen":16.19,"low":15.94,"changeOverTime":-0.23420427553444179,"fHigh":16.19,"changePercent":-0.0171,"id":"HISTORICAL_PRICES","marketChangeOverTime":-0.23420427553444179,"close":16.12,"key":"TME","fLow":15.94,"uHigh":16.19,"uVolume":8747698,"change":-0.2799999999999976,"uLow":15.94,"fVolume":8747698,"label":"Nov 18, 20","volume":8747698,"updated":1606834800000,"open":16.19},
{"date":"2020-11-17","symbol":"TME","subkey":"","fClose":16.21,"uOpen":16.1,"uClose":16.21,"high":16.36,"fOpen":16.1,"low":15.99,"changeOverTime":-0.22992874109263656,"fHigh":16.36,"changePercent":0.0056,"id":"HISTORICAL_PRICES","marketChangeOverTime":-0.22992874109263656,"close":16.21,"key":"TME","fLow":15.99,"uHigh":16.36,"uVolume":5205096,"change":0.08999999999999986,"uLow":15.99,"fVolume":5205096,"label":"Nov 17, 20","volume":5205096,"updated":1606830572000,"open":16.1},
{"date":"2020-11-16","symbol":"TME","subkey":"","fClose":16.1,"uOpen":16.49,"uClose":16.1,"high":16.8,"fOpen":16.49,"low":16.095,"changeOverTime":-0.23515439429928736,"fHigh":16.8,"changePercent":-0.0068,"id":"HISTORICAL_PRICES","marketChangeOverTime":-0.23515439429928736,"close":16.1,"key":"TME","fLow":16.095,"uHigh":16.8,"uVolume":5635884,"change":-0.10999999999999943,"uLow":16.095,"fVolume":5635884,"label":"Nov 16, 20","volume":5635884,"updated":1606830572000,"open":16.49},
{"date":"2020-11-13","symbol":"TME","subkey":"","fClose":16.49,"uOpen":16.03,"uClose":16.49,"high":16.6482,"fOpen":16.03,"low":16.03,"changeOverTime":-0.2166270783847982,"fHigh":16.6482,"changePercent":0.0242,"id":"HISTORICAL_PRICES","marketChangeOverTime":-0.2166270783847982,"close":16.49,"key":"TME","fLow":16.03,"uHigh":16.6482,"uVolume":12695235,"change":0.389999999999997,"uLow":16.03,"fVolume":12695235,"label":"Nov 13, 20","volume":12695235,"updated":1606830572000,"open":16.03},
{"date":"2020-11-12","symbol":"TME","subkey":"","fClose":15.99,"uOpen":15.32,"uClose":15.99,"high":16.3,"fOpen":15.32,"low":15.31,"changeOverTime":-0.24038004750593825,"fHigh":16.3,"changePercent":-0.0303,"id":"HISTORICAL_PRICES","marketChangeOverTime":-0.24038004750593825,"close":15.99,"key":"TME","fLow":15.31,"uHigh":16.3,"uVolume":9738389,"change":-0.4999999999999982,"uLow":15.31,"fVolume":9738389,"label":"Nov 12, 20","volume":9738389,"updated":1606830572000,"open":15.32},
{"date":"2020-11-11","symbol":"TME","subkey":"","fClose":15.31,"uOpen":15.15,"uClose":15.31,"high":15.375,"fOpen":15.15,"low":14.2,"changeOverTime":-0.27268408551068885,"fHigh":15.375,"changePercent":-0.0425,"id":"HISTORICAL_PRICES","marketChangeOverTime":-0.27268408551068885,"close":15.31,"key":"TME","fLow":14.2,"uHigh":15.375,"uVolume":16529677,"change":-0.6799999999999997,"uLow":14.2,"fVolume":16529677,"label":"Nov 11, 20","volume":16529677,"updated":1606830572000,"open":15.15},
{"date":"2020-11-10","symbol":"TME","subkey":"","fClose":14.95,"uOpen":15.08,"uClose":14.95,"high":15.27,"fOpen":15.08,"low":14.74,"changeOverTime":-0.2897862232779098,"fHigh":15.27,"changePercent":-0.0235,"id":"HISTORICAL_PRICES","marketChangeOverTime":-0.2897862232779098,"close":14.95,"key":"TME","fLow":14.74,"uHigh":15.27,"uVolume":23923994,"change":-0.3600000000000012,"uLow":14.74,"fVolume":23923994,"label":"Nov 10, 20","volume":23923994,"updated":1606830572000,"open":15.08},
{"date":"2020-11-09","symbol":"TME","subkey":"","fClose":15.12,"uOpen":15.32,"uClose":15.12,"high":15.74,"fOpen":15.32,"low":14.98,"changeOverTime":-0.2817102137767222,"fHigh":15.74,"changePercent":0.0114,"id":"HISTORICAL_PRICES","marketChangeOverTime":-0.2817102137767222,"close":15.12,"key":"TME","fLow":14.98,"uHigh":15.74,"uVolume":16440918,"change":0.16999999999999993,"uLow":14.98,"fVolume":16440918,"label":"Nov 9, 20","volume":16440918,"updated":1606830572000,"open":15.32},
{"date":"2020-11-06","symbol":"TME","subkey":"","fClose":15.27,"uOpen":15.43,"uClose":15.27,"high":15.5,"fOpen":15.43,"low":15.21,"changeOverTime":-0.2745843230403801,"fHigh":15.5,"changePercent":0.0099,"id":"HISTORICAL_PRICES","marketChangeOverTime":-0.2745843230403801,"close":15.27,"key":"TME","fLow":15.21,"uHigh":15.5,"uVolume":14044242,"change":0.15000000000000036,"uLow":15.21,"fVolume":14044242,"label":"Nov 6, 20","volume":14044242,"updated":1606830572000,"open":15.43},
{"date":"2020-11-05","symbol":"TME","subkey":"","fClose":15.86,"uOpen":15.33,"uClose":15.86,"high":15.925,"fOpen":15.33,"low":15.205,"changeOverTime":-0.24655581947743474,"fHigh":15.925,"changePercent":0.0386,"id":"HISTORICAL_PRICES","marketChangeOverTime":-0.24655581947743474,"close":15.86,"key":"TME","fLow":15.205,"uHigh":15.925,"uVolume":6392476,"change":0.5899999999999999,"uLow":15.205,"fVolume":6392476,"label":"Nov 5, 20","volume":6392476,"updated":1606830572000,"open":15.33},
{"date":"2020-11-04","symbol":"TME","subkey":"","fClose":15.37,"uOpen":15.02,"uClose":15.37,"high":15.5,"fOpen":15.02,"low":14.93,"changeOverTime":-0.26983372921615206,"fHigh":15.5,"changePercent":-0.0309,"id":"HISTORICAL_PRICES","marketChangeOverTime":-0.26983372921615206,"close":15.37,"key":"TME","fLow":14.93,"uHigh":15.5,"uVolume":9651715,"change":-0.4900000000000002,"uLow":14.93,"fVolume":9651715,"label":"Nov 4, 20","volume":9651715,"updated":1606830572000,"open":15.02},
{"date":"2020-11-03","symbol":"TME","subkey":"","fClose":14.87,"uOpen":14.66,"uClose":14.87,"high":14.905,"fOpen":14.66,"low":14.5,"changeOverTime":-0.29358669833729223,"fHigh":14.905,"changePercent":-0.0325,"id":"HISTORICAL_PRICES","marketChangeOverTime":-0.29358669833729223,"close":14.87,"key":"TME","fLow":14.5,"uHigh":14.905,"uVolume":7683921,"change":-0.5,"uLow":14.5,"fVolume":7683921,"label":"Nov 3, 20","volume":7683921,"updated":1606830572000,"open":14.66},
{"date":"2020-11-02","symbol":"TME","subkey":"","fClose":14.75,"uOpen":15.02,"uClose":14.75,"high":15.02,"fOpen":15.02,"low":14.5,"changeOverTime":-0.2992874109263658,"fHigh":15.02,"changePercent":-0.0081,"id":"HISTORICAL_PRICES","marketChangeOverTime":-0.2992874109263658,"close":14.75,"key":"TME","fLow":14.5,"uHigh":15.02,"uVolume":12358678,"change":-0.11999999999999922,"uLow":14.5,"fVolume":12358678,"label":"Nov 2, 20","volume":12358678,"updated":1606830572000,"open":15.02},
{"date":"2020-10-30","symbol":"TME","subkey":"","fClose":14.88,"uOpen":14.6,"uClose":14.88,"high":14.92,"fOpen":14.6,"low":14.36,"changeOverTime":-0.29311163895486936,"fHigh":14.92,"changePercent":0.0088,"id":"HISTORICAL_PRICES","marketChangeOverTime":-0.29311163895486936,"close":14.88,"key":"TME","fLow":14.36,"uHigh":14.92,"uVolume":13120148,"change":0.13000000000000078,"uLow":14.36,"fVolume":13120148,"label":"Oct 30, 20","volume":13120148,"updated":1606830572000,"open":14.6},
{"date":"2020-10-29","symbol":"TME","subkey":"","fClose":14.71,"uOpen":14.5,"uClose":14.71,"high":14.865,"fOpen":14.5,"low":14.46,"changeOverTime":-0.301187648456057,"fHigh":14.865,"changePercent":-0.0114,"id":"HISTORICAL_PRICES","marketChangeOverTime":-0.301187648456057,"close":14.71,"key":"TME","fLow":14.46,"uHigh":14.865,"uVolume":10889447,"change":-0.16999999999999993,"uLow":14.46,"fVolume":10889447,"label":"Oct 29, 20","volume":10889447,"updated":1606830572000,"open":14.5},
{"date":"2020-10-28","symbol":"TME","subkey":"","fClose":14.54,"uOpen":14.75,"uClose":14.54,"high":14.75,"fOpen":14.75,"low":14.14,"changeOverTime":-0.3092636579572447,"fHigh":14.75,"changePercent":-0.0116,"id":"HISTORICAL_PRICES","marketChangeOverTime":-0.3092636579572447,"close":14.54,"key":"TME","fLow":14.14,"uHigh":14.75,"uVolume":11852288,"change":-0.1700000000000017,"uLow":14.14,"fVolume":11852288,"label":"Oct 28, 20","volume":11852288,"updated":1606830572000,"open":14.75},
{"date":"2020-10-27","symbol":"TME","subkey":"","fClose":15,"uOpen":15,"uClose":15,"high":15.08,"fOpen":15,"low":14.51,"changeOverTime":-0.28741092636579574,"fHigh":15.08,"changePercent":0.0316,"id":"HISTORICAL_PRICES","marketChangeOverTime":-0.28741092636579574,"close":15,"key":"TME","fLow":14.51,"uHigh":15.08,"uVolume":12446563,"change":0.46000000000000085,"uLow":14.51,"fVolume":12446563,"label":"Oct 27, 20","volume":12446563,"updated":1606830572000,"open":15},
{"date":"2020-10-26","symbol":"TME","subkey":"","fClose":15.04,"uOpen":14.84,"uClose":15.04,"high":15.14,"fOpen":14.84,"low":14.785,"changeOverTime":-0.2855106888361046,"fHigh":15.14,"changePercent":0.0027,"id":"HISTORICAL_PRICES","marketChangeOverTime":-0.2855106888361046,"close":15.04,"key":"TME","fLow":14.785,"uHigh":15.14,"uVolume":11316433,"change":0.03999999999999915,"uLow":14.785,"fVolume":11316433,"label":"Oct 26, 20","volume":11316433,"updated":1606830572000,"open":14.84},
{"date":"2020-10-23","symbol":"TME","subkey":"","fClose":14.92,"uOpen":14.6,"uClose":14.92,"high":15.02,"fOpen":14.6,"low":14.58,"changeOverTime":-0.29121140142517815,"fHigh":15.02,"changePercent":-0.008,"id":"HISTORICAL_PRICES","marketChangeOverTime":-0.29121140142517815,"close":14.92,"key":"TME","fLow":14.58,"uHigh":15.02,"uVolume":4510324,"change":-0.11999999999999922,"uLow":14.58,"fVolume":4510324,"label":"Oct 23, 20","volume":4510324,"updated":1606830572000,"open":14.6},
{"date":"2020-10-22","symbol":"TME","subkey":"","fClose":14.69,"uOpen":14.35,"uClose":14.69,"high":14.77,"fOpen":14.35,"low":14.1,"changeOverTime":-0.3021377672209027,"fHigh":14.77,"changePercent":-0.0154,"id":"HISTORICAL_PRICES","marketChangeOverTime":-0.3021377672209027,"close":14.69,"key":"TME","fLow":14.1,"uHigh":14.77,"uVolume":6029814,"change":-0.23000000000000043,"uLow":14.1,"fVolume":6029814,"label":"Oct 22, 20","volume":6029814,"updated":1606830572000,"open":14.35},
{"date":"2020-10-21","symbol":"TME","subkey":"","fClose":14.38,"uOpen":14.09,"uClose":14.38,"high":14.42,"fOpen":14.09,"low":13.94,"changeOverTime":-0.31686460807600947,"fHigh":14.42,"changePercent":-0.0211,"id":"HISTORICAL_PRICES","marketChangeOverTime":-0.31686460807600947,"close":14.38,"key":"TME","fLow":13.94,"uHigh":14.42,"uVolume":10334580,"change":-0.3099999999999987,"uLow":13.94,"fVolume":10334580,"label":"Oct 21, 20","volume":10334580,"updated":1606830572000,"open":14.09},
{"date":"2020-10-20","symbol":"TME","subkey":"","fClose":14.01,"uOpen":14.15,"uClose":14.01,"high":14.25,"fOpen":14.15,"low":14,"changeOverTime":-0.33444180522565325,"fHigh":14.25,"changePercent":-0.0257,"id":"HISTORICAL_PRICES","marketChangeOverTime":-0.33444180522565325,"close":14.01,"key":"TME","fLow":14,"uHigh":14.25,"uVolume":5573577,"change":-0.370000000000001,"uLow":14,"fVolume":5573577,"label":"Oct 20, 20","volume":5573577,"updated":1606830572000,"open":14.15},
{"date":"2020-10-19","symbol":"TME","subkey":"","fClose":14.15,"uOpen":14.38,"uClose":14.15,"high":14.39,"fOpen":14.38,"low":13.92,"changeOverTime":-0.32779097387173395,"fHigh":14.39,"changePercent":0.01,"id":"HISTORICAL_PRICES","marketChangeOverTime":-0.32779097387173395,"close":14.15,"key":"TME","fLow":13.92,"uHigh":14.39,"uVolume":7586116,"change":0.14000000000000057,"uLow":13.92,"fVolume":7586116,"label":"Oct 19, 20","volume":7586116,"updated":1606830572000,"open":14.38},
{"date":"2020-10-16","symbol":"TME","subkey":"","fClose":14.25,"uOpen":14.22,"uClose":14.25,"high":14.39,"fOpen":14.22,"low":14.145,"changeOverTime":-0.32304038004750596,"fHigh":14.39,"changePercent":0.0071,"id":"HISTORICAL_PRICES","marketChangeOverTime":-0.32304038004750596,"close":14.25,"key":"TME","fLow":14.145,"uHigh":14.39,"uVolume":5959519,"change":0.09999999999999964,"uLow":14.145,"fVolume":5959519,"label":"Oct 16, 20","volume":5959519,"updated":1606830572000,"open":14.22},
{"date":"2020-10-15","symbol":"TME","subkey":"","fClose":14.3,"uOpen":14.14,"uClose":14.3,"high":14.33,"fOpen":14.14,"low":13.85,"changeOverTime":-0.32066508313539194,"fHigh":14.33,"changePercent":0.0035,"id":"HISTORICAL_PRICES","marketChangeOverTime":-0.32066508313539194,"close":14.3,"key":"TME","fLow":13.85,"uHigh":14.33,"uVolume":5112352,"change":0.05000000000000071,"uLow":13.85,"fVolume":5112352,"label":"Oct 15, 20","volume":5112352,"updated":1606830572000,"open":14.14},
{"date":"2020-10-14","symbol":"TME","subkey":"","fClose":14.29,"uOpen":14.34,"uClose":14.29,"high":14.46,"fOpen":14.34,"low":14.11,"changeOverTime":-0.3211401425178148,"fHigh":14.46,"changePercent":-0.0007,"id":"HISTORICAL_PRICES","marketChangeOverTime":-0.3211401425178148,"close":14.29,"key":"TME","fLow":14.11,"uHigh":14.46,"uVolume":7335083,"change":-0.010000000000001563,"uLow":14.11,"fVolume":7335083,"label":"Oct 14, 20","volume":7335083,"updated":1606830572000,"open":14.34},
{"date":"2020-10-13","symbol":"TME","subkey":"","fClose":14.26,"uOpen":14.45,"uClose":14.26,"high":14.48,"fOpen":14.45,"low":14.18,"changeOverTime":-0.32256532066508314,"fHigh":14.48,"changePercent":-0.0021,"id":"HISTORICAL_PRICES","marketChangeOverTime":-0.32256532066508314,"close":14.26,"key":"TME","fLow":14.18,"uHigh":14.48,"uVolume":6170458,"change":-0.02999999999999936,"uLow":14.18,"fVolume":6170458,"label":"Oct 13, 20","volume":6170458,"updated":1606830572000,"open":14.45},
{"date":"2020-10-12","symbol":"TME","subkey":"","fClose":14.31,"uOpen":14.73,"uClose":14.31,"high":14.73,"fOpen":14.73,"low":14.25,"changeOverTime":-0.3201900237529691,"fHigh":14.73,"changePercent":0.0035,"id":"HISTORICAL_PRICES","marketChangeOverTime":-0.3201900237529691,"close":14.31,"key":"TME","fLow":14.25,"uHigh":14.73,"uVolume":6243579,"change":0.05000000000000071,"uLow":14.25,"fVolume":6243579,"label":"Oct 12, 20","volume":6243579,"updated":1606830572000,"open":14.73},
{"date":"2020-10-09","symbol":"TME","subkey":"","fClose":14.52,"uOpen":14.44,"uClose":14.52,"high":14.7,"fOpen":14.44,"low":14.4,"changeOverTime":-0.31021377672209033,"fHigh":14.7,"changePercent":0.0147,"id":"HISTORICAL_PRICES","marketChangeOverTime":-0.31021377672209033,"close":14.52,"key":"TME","fLow":14.4,"uHigh":14.7,"uVolume":3426926,"change":0.20999999999999908,"uLow":14.4,"fVolume":3426926,"label":"Oct 9, 20","volume":3426926,"updated":1606830572000,"open":14.44}]